{"08":{"t":1,"n":"CJK UNIFIED IDEOGRAPH-4008","V":[{"i":65024,"t":2,"c":3,"n":"CJK COMPATIBILITY IDEOGRAPH-2F93F"}]},"18":{"t":1,"n":"CJK UNIFIED IDEOGRAPH-4018","V":[{"i":65024,"t":2,"c":3,"n":"CJK COMPATIBILITY IDEOGRAPH-FAD3"}]},"39":{"t":1,"n":"CJK UNIFIED IDEOGRAPH-4039","V":[{"i":65024,"t":2,"c":3,"n":"CJK COMPATIBILITY IDEOGRAPH-FAD4"},{"i":65025,"t":2,"c":3,"n":"CJK COMPATIBILITY IDEOGRAPH-2F949"}]},"46":{"t":1,"n":"CJK UNIFIED IDEOGRAPH-4046","V":[{"i":65024,"t":2,"c":3,"n":"CJK COMPATIBILITY IDEOGRAPH-2F94B"}]},"96":{"t":1,"n":"CJK UNIFIED IDEOGRAPH-4096","V":[{"i":65024,"t":2,"c":3,"n":"CJK COMPATIBILITY IDEOGRAPH-2F94C"}]},"E3":{"t":1,"n":"CJK UNIFIED IDEOGRAPH-40E3","V":[{"i":65024,"t":2,"c":3,"n":"CJK COMPATIBILITY IDEOGRAPH-2F951"}]}}