{"01":{"t":1,"n":"CJK UNIFIED IDEOGRAPH-8401","V":[{"i":917760,"t":1,"c":"Adobe-Japan1","n":"CID+17081"},{"i":917761,"t":1,"c":"Hanyo-Denshi","n":"JB5637"},{"i":917761,"t":1,"c":"Moji_Joho","n":"MJ022191"},{"i":917762,"t":1,"c":"Hanyo-Denshi","n":"JTB9CD"},{"i":917762,"t":1,"c":"Moji_Joho","n":"MJ022192"}]},"03":{"t":1,"n":"CJK UNIFIED IDEOGRAPH-8403","V":[{"i":917760,"t":1,"c":"Adobe-Japan1","n":"CID+6381"},{"i":917761,"t":1,"c":"Hanyo-Denshi","n":"JA7236"},{"i":917761,"t":1,"c":"Moji_Joho","n":"MJ022194"},{"i":917762,"t":1,"c":"Hanyo-Denshi","n":"JTB996"},{"i":917762,"t":1,"c":"Moji_Joho","n":"MJ022196"},{"i":917763,"t":1,"c":"Hanyo-Denshi","n":"KS351470"},{"i":917763,"t":1,"c":"Moji_Joho","n":"MJ022195"},{"i":917764,"t":1,"c":"Hanyo-Denshi","n":"TK01077470"}]},"04":{"t":1,"n":"CJK UNIFIED IDEOGRAPH-8404","V":[{"i":917760,"t":1,"c":"Adobe-Japan1","n":"CID+3218"},{"i":917761,"t":1,"c":"Hanyo-Denshi","n":"JA3826"},{"i":917761,"t":1,"c":"Moji_Joho","n":"MJ022198"},{"i":917762,"t":1,"c":"Hanyo-Denshi","n":"KS351480"},{"i":917762,"t":1,"c":"Moji_Joho","n":"MJ022199"},{"i":917763,"t":1,"c":"Hanyo-Denshi","n":"KS353120"},{"i":917763,"t":1,"c":"Moji_Joho","n":"MJ058494"}]},"06":{"t":1,"n":"CJK UNIFIED IDEOGRAPH-8406","V":[{"i":917760,"t":1,"c":"Adobe-Japan1","n":"CID+17082"},{"i":917761,"t":1,"c":"Hanyo-Denshi","n":"JB5638"},{"i":917761,"t":1,"c":"Moji_Joho","n":"MJ022201"},{"i":917762,"t":1,"c":"Hanyo-Denshi","n":"KS351510"},{"i":917762,"t":1,"c":"Moji_Joho","n":"MJ022202"}]},"07":{"t":1,"n":"CJK UNIFIED IDEOGRAPH-8407","V":[{"i":917760,"t":1,"c":"Adobe-Japan1","n":"CID+6386"},{"i":917761,"t":1,"c":"Hanyo-Denshi","n":"JA7241"},{"i":917761,"t":1,"c":"Moji_Joho","n":"MJ022203"},{"i":917762,"t":1,"c":"Hanyo-Denshi","n":"KS351520"},{"i":917762,"t":1,"c":"Moji_Joho","n":"MJ022204"}]},"0A":{"t":1,"n":"CJK UNIFIED IDEOGRAPH-840A","V":[{"i":917760,"t":1,"c":"Adobe-Japan1","n":"CID+7807"},{"i":917761,"t":1,"c":"Hanyo-Denshi","n":"JB5639"},{"i":917761,"t":1,"c":"Moji_Joho","n":"MJ022207"},{"i":917762,"t":1,"c":"Hanyo-Denshi","n":"KS351580"},{"i":917762,"t":1,"c":"Moji_Joho","n":"MJ022208"}]},"0B":{"t":1,"n":"CJK UNIFIED IDEOGRAPH-840B","V":[{"i":917760,"t":1,"c":"Adobe-Japan1","n":"CID+6383"},{"i":917761,"t":1,"c":"Hanyo-Denshi","n":"JA7238"},{"i":917761,"t":1,"c":"Moji_Joho","n":"MJ022209"},{"i":917762,"t":1,"c":"Hanyo-Denshi","n":"KS351600"},{"i":917762,"t":1,"c":"Moji_Joho","n":"MJ022210"},{"i":917763,"t":1,"c":"Hanyo-Denshi","n":"JTB995"},{"i":917763,"t":1,"c":"Moji_Joho","n":"MJ022211"}]},"0C":{"t":1,"n":"CJK UNIFIED IDEOGRAPH-840C","V":[{"i":917760,"t":1,"c":"Adobe-Japan1","n":"CID+3670"},{"i":917761,"t":1,"c":"Adobe-Japan1","n":"CID+14026"},{"i":917762,"t":1,"c":"Hanyo-Denshi","n":"JA4308"},{"i":917762,"t":1,"c":"Moji_Joho","n":"MJ022212"},{"i":917763,"t":1,"c":"Hanyo-Denshi","n":"KS351610"},{"i":917763,"t":1,"c":"Moji_Joho","n":"MJ022213"}]},"0D":{"t":1,"n":"CJK UNIFIED IDEOGRAPH-840D","V":[{"i":917760,"t":1,"c":"Adobe-Japan1","n":"CID+6389"},{"i":917761,"t":1,"c":"Hanyo-Denshi","n":"JA7244"},{"i":917761,"t":1,"c":"Moji_Joho","n":"MJ022214"},{"i":917762,"t":1,"c":"Hanyo-Denshi","n":"KS351620"},{"i":917762,"t":1,"c":"Moji_Joho","n":"MJ022215"},{"i":917763,"t":1,"c":"Hanyo-Denshi","n":"FT2481"},{"i":917763,"t":1,"c":"Moji_Joho","n":"MJ022216"}]},"0E":{"t":1,"n":"CJK UNIFIED IDEOGRAPH-840E","V":[{"i":917760,"t":1,"c":"Adobe-Japan1","n":"CID+1188"},{"i":917761,"t":1,"c":"Hanyo-Denshi","n":"JA1664"},{"i":917761,"t":1,"c":"Moji_Joho","n":"MJ022217"},{"i":917762,"t":1,"c":"Hanyo-Denshi","n":"KS351650"},{"i":917762,"t":1,"c":"Moji_Joho","n":"MJ022218"}]},"0F":{"t":1,"n":"CJK UNIFIED IDEOGRAPH-840F","V":[{"i":917760,"t":1,"c":"Adobe-Japan1","n":"CID+15060"},{"i":917761,"t":1,"c":"Adobe-Japan1","n":"CID+20203"},{"i":917762,"t":1,"c":"Hanyo-Denshi","n":"JB5640"},{"i":917762,"t":1,"c":"Moji_Joho","n":"MJ022219"},{"i":917763,"t":1,"c":"Hanyo-Denshi","n":"KS351660"},{"i":917763,"t":1,"c":"Moji_Joho","n":"MJ022220"}]},"11":{"t":1,"n":"CJK UNIFIED IDEOGRAPH-8411","V":[{"i":917760,"t":1,"c":"Adobe-Japan1","n":"CID+15061"},{"i":917761,"t":1,"c":"Hanyo-Denshi","n":"JB5641"},{"i":917761,"t":1,"c":"Moji_Joho","n":"MJ022222"},{"i":917762,"t":1,"c":"Hanyo-Denshi","n":"JTB9D1"},{"i":917762,"t":1,"c":"Moji_Joho","n":"MJ022223"}]},"13":{"t":1,"n":"CJK UNIFIED IDEOGRAPH-8413","V":[{"i":917760,"t":1,"c":"Adobe-Japan1","n":"CID+6377"},{"i":917761,"t":1,"c":"Hanyo-Denshi","n":"JA7232"},{"i":917761,"t":1,"c":"Moji_Joho","n":"MJ022225"},{"i":917762,"t":1,"c":"Hanyo-Denshi","n":"JTB9AA"},{"i":917762,"t":1,"c":"Moji_Joho","n":"MJ022227"},{"i":917763,"t":1,"c":"Hanyo-Denshi","n":"JTB9A9"},{"i":917763,"t":1,"c":"Moji_Joho","n":"MJ022226"},{"i":917764,"t":1,"c":"Hanyo-Denshi","n":"TK01079780"}]},"15":{"t":1,"n":"CJK UNIFIED IDEOGRAPH-8415","V":[{"i":917760,"t":1,"c":"Adobe-Japan1","n":"CID+18505"},{"i":917761,"t":1,"c":"Hanyo-Denshi","n":"JB5642"},{"i":917761,"t":1,"c":"Moji_Joho","n":"MJ022229"},{"i":917762,"t":1,"c":"Hanyo-Denshi","n":"KS351930"},{"i":917762,"t":1,"c":"Moji_Joho","n":"MJ022231"},{"i":917763,"t":1,"c":"Moji_Joho","n":"MJ022230"}]},"17":{"t":1,"n":"CJK UNIFIED IDEOGRAPH-8417","V":[{"i":917760,"t":1,"c":"Adobe-Japan1","n":"CID+18507"}]},"19":{"t":1,"n":"CJK UNIFIED IDEOGRAPH-8419","V":[{"i":917760,"t":1,"c":"Adobe-Japan1","n":"CID+22334"},{"i":917761,"t":1,"c":"Hanyo-Denshi","n":"JB5643"},{"i":917761,"t":1,"c":"Moji_Joho","n":"MJ022234"},{"i":917762,"t":1,"c":"Hanyo-Denshi","n":"KS352140"},{"i":917762,"t":1,"c":"Moji_Joho","n":"MJ022235"}]},"1E":{"t":1,"n":"CJK UNIFIED IDEOGRAPH-841E","V":[{"i":917760,"t":1,"c":"Hanyo-Denshi","n":"JT841E"},{"i":917760,"t":1,"c":"Moji_Joho","n":"MJ022236"},{"i":917761,"t":1,"c":"Hanyo-Denshi","n":"JTB9C9"},{"i":917761,"t":1,"c":"Moji_Joho","n":"MJ022237"}]},"20":{"t":1,"n":"CJK UNIFIED IDEOGRAPH-8420","V":[{"i":917760,"t":1,"c":"Adobe-Japan1","n":"CID+6391"},{"i":917761,"t":1,"c":"Adobe-Japan1","n":"CID+14203"},{"i":917762,"t":1,"c":"Hanyo-Denshi","n":"JA7246"},{"i":917762,"t":1,"c":"Moji_Joho","n":"MJ022239"},{"i":917763,"t":1,"c":"Hanyo-Denshi","n":"KS352890"},{"i":917763,"t":1,"c":"Moji_Joho","n":"MJ022240"},{"i":917764,"t":1,"c":"Hanyo-Denshi","n":"FT2482"},{"i":917764,"t":1,"c":"Moji_Joho","n":"MJ022241"},{"i":917765,"t":1,"c":"Hanyo-Denshi","n":"TK01079020"}]},"22":{"t":1,"n":"CJK UNIFIED IDEOGRAPH-8422","V":[{"i":917760,"t":1,"c":"Adobe-Japan1","n":"CID+6390"},{"i":917761,"t":1,"c":"Adobe-Japan1","n":"CID+7999"},{"i":917762,"t":1,"c":"Hanyo-Denshi","n":"JA7245"},{"i":917762,"t":1,"c":"Moji_Joho","n":"MJ022243"},{"i":917763,"t":1,"c":"Hanyo-Denshi","n":"KS352840"},{"i":917763,"t":1,"c":"Moji_Joho","n":"MJ022245"},{"i":917764,"t":1,"c":"Hanyo-Denshi","n":"JTB9B6"},{"i":917764,"t":1,"c":"Moji_Joho","n":"MJ022244"}]},"29":{"t":1,"n":"CJK UNIFIED IDEOGRAPH-8429","V":[{"i":917760,"t":1,"c":"Adobe-Japan1","n":"CID+3361"},{"i":917761,"t":1,"c":"Hanyo-Denshi","n":"JA3975"},{"i":917761,"t":1,"c":"Moji_Joho","n":"MJ022248"},{"i":917762,"t":1,"c":"Hanyo-Denshi","n":"JTB9F9"},{"i":917762,"t":1,"c":"Moji_Joho","n":"MJ022249"}]},"2A":{"t":1,"n":"CJK UNIFIED IDEOGRAPH-842A","V":[{"i":917760,"t":1,"c":"Adobe-Japan1","n":"CID+6397"},{"i":917761,"t":1,"c":"Hanyo-Denshi","n":"JA7252"},{"i":917761,"t":1,"c":"Moji_Joho","n":"MJ022250"},{"i":917762,"t":1,"c":"Hanyo-Denshi","n":"KS353290"},{"i":917762,"t":1,"c":"Moji_Joho","n":"MJ022251"}]},"2B":{"t":1,"n":"CJK UNIFIED IDEOGRAPH-842B","V":[{"i":917760,"t":1,"c":"Hanyo-Denshi","n":"IP842B"},{"i":917760,"t":1,"c":"Moji_Joho","n":"MJ022252"},{"i":917761,"t":1,"c":"Hanyo-Denshi","n":"KS353320"},{"i":917761,"t":1,"c":"Moji_Joho","n":"MJ022253"}]},"2C":{"t":1,"n":"CJK UNIFIED IDEOGRAPH-842C","V":[{"i":917760,"t":1,"c":"Adobe-Japan1","n":"CID+6408"},{"i":917761,"t":1,"c":"Hanyo-Denshi","n":"JA7263"},{"i":917761,"t":1,"c":"Moji_Joho","n":"MJ022254"},{"i":917762,"t":1,"c":"Hanyo-Denshi","n":"JTB9E5"},{"i":917762,"t":1,"c":"Moji_Joho","n":"MJ022257"},{"i":917763,"t":1,"c":"Hanyo-Denshi","n":"KS355970"},{"i":917763,"t":1,"c":"Moji_Joho","n":"MJ022256"},{"i":917764,"t":1,"c":"Hanyo-Denshi","n":"KS353330"},{"i":917764,"t":1,"c":"Moji_Joho","n":"MJ022255"},{"i":917765,"t":1,"c":"Hanyo-Denshi","n":"TK01007760"}]},"2F":{"t":1,"n":"CJK UNIFIED IDEOGRAPH-842F","V":[{"i":917760,"t":1,"c":"Adobe-Japan1","n":"CID+22336"},{"i":917761,"t":1,"c":"Hanyo-Denshi","n":"JB5645"},{"i":917761,"t":1,"c":"Moji_Joho","n":"MJ022260"},{"i":917762,"t":1,"c":"Hanyo-Denshi","n":"KS356050"},{"i":917762,"t":1,"c":"Moji_Joho","n":"MJ022261"}]},"31":{"t":1,"n":"CJK UNIFIED IDEOGRAPH-8431","V":[{"i":917760,"t":1,"c":"Adobe-Japan1","n":"CID+1500"},{"i":917761,"t":1,"c":"Hanyo-Denshi","n":"JA1994"},{"i":917761,"t":1,"c":"Moji_Joho","n":"MJ022263"},{"i":917762,"t":1,"c":"Hanyo-Denshi","n":"JTB9ED"},{"i":917762,"t":1,"c":"Moji_Joho","n":"MJ022264"},{"i":917763,"t":1,"c":"Hanyo-Denshi","n":"TK01078760"}]},"35":{"t":1,"n":"CJK UNIFIED IDEOGRAPH-8435","V":[{"i":917760,"t":1,"c":"Adobe-Japan1","n":"CID+6411"},{"i":917761,"t":1,"c":"Hanyo-Denshi","n":"JA7266"},{"i":917761,"t":1,"c":"Moji_Joho","n":"MJ022268"},{"i":917762,"t":1,"c":"Hanyo-Denshi","n":"KS353440"},{"i":917762,"t":1,"c":"Moji_Joho","n":"MJ022269"}]},"36":{"t":1,"n":"CJK UNIFIED IDEOGRAPH-8436","V":[{"i":917760,"t":1,"c":"Hanyo-Denshi","n":"IP8436"},{"i":917761,"t":1,"c":"Hanyo-Denshi","n":"KS353450"}]},"38":{"t":1,"n":"CJK UNIFIED IDEOGRAPH-8438","V":[{"i":917760,"t":1,"c":"Adobe-Japan1","n":"CID+6393"},{"i":917761,"t":1,"c":"Hanyo-Denshi","n":"JA7248"},{"i":917761,"t":1,"c":"Moji_Joho","n":"MJ022273"},{"i":917762,"t":1,"c":"Hanyo-Denshi","n":"KS353490"},{"i":917762,"t":1,"c":"Moji_Joho","n":"MJ022274"}]},"39":{"t":1,"n":"CJK UNIFIED IDEOGRAPH-8439","V":[{"i":917760,"t":1,"c":"Adobe-Japan1","n":"CID+18508"},{"i":917761,"t":1,"c":"Hanyo-Denshi","n":"JB5646"},{"i":917761,"t":1,"c":"Moji_Joho","n":"MJ022275"},{"i":917762,"t":1,"c":"Hanyo-Denshi","n":"KS353510"},{"i":917762,"t":1,"c":"Moji_Joho","n":"MJ022276"}]},"3B":{"t":1,"n":"CJK UNIFIED IDEOGRAPH-843B","V":[{"i":917760,"t":1,"c":"Hanyo-Denshi","n":"IP843B"},{"i":917760,"t":1,"c":"Moji_Joho","n":"MJ022278"},{"i":917761,"t":1,"c":"Hanyo-Denshi","n":"KS353530"},{"i":917761,"t":1,"c":"Moji_Joho","n":"MJ022279"}]},"3C":{"t":1,"n":"CJK UNIFIED IDEOGRAPH-843C","V":[{"i":917760,"t":1,"c":"Adobe-Japan1","n":"CID+6398"},{"i":917761,"t":1,"c":"Hanyo-Denshi","n":"JA7253"},{"i":917761,"t":1,"c":"Moji_Joho","n":"MJ022280"},{"i":917762,"t":1,"c":"Hanyo-Denshi","n":"JTB9EC"},{"i":917762,"t":1,"c":"Moji_Joho","n":"MJ022281"}]},"3D":{"t":1,"n":"CJK UNIFIED IDEOGRAPH-843D","V":[{"i":65024,"t":2,"c":3,"n":"CJK COMPATIBILITY IDEOGRAPH-F918"},{"i":917760,"t":1,"c":"Adobe-Japan1","n":"CID+3928"},{"i":917761,"t":1,"c":"Hanyo-Denshi","n":"JA4578"},{"i":917761,"t":1,"c":"Moji_Joho","n":"MJ022282"},{"i":917762,"t":1,"c":"Hanyo-Denshi","n":"KS353550"},{"i":917762,"t":1,"c":"Moji_Joho","n":"MJ022283"}]},"3F":{"t":1,"n":"CJK UNIFIED IDEOGRAPH-843F","V":[{"i":917760,"t":1,"c":"Hanyo-Denshi","n":"IP843F"},{"i":917761,"t":1,"c":"Hanyo-Denshi","n":"KS353580"}]},"41":{"t":1,"n":"CJK UNIFIED IDEOGRAPH-8441","V":[{"i":917760,"t":1,"c":"Hanyo-Denshi","n":"IP8441"},{"i":917760,"t":1,"c":"Moji_Joho","n":"MJ022288"},{"i":917761,"t":1,"c":"Hanyo-Denshi","n":"JTB9F4"},{"i":917761,"t":1,"c":"Moji_Joho","n":"MJ022289"}]},"45":{"t":1,"n":"CJK UNIFIED IDEOGRAPH-8445","V":[{"i":917760,"t":1,"c":"Adobe-Japan1","n":"CID+22337"},{"i":917761,"t":1,"c":"Hanyo-Denshi","n":"JB5647"},{"i":917761,"t":1,"c":"Moji_Joho","n":"MJ022293"},{"i":917762,"t":1,"c":"Hanyo-Denshi","n":"KS353710"},{"i":917762,"t":1,"c":"Moji_Joho","n":"MJ022294"}]},"46":{"t":1,"n":"CJK UNIFIED IDEOGRAPH-8446","V":[{"i":917760,"t":1,"c":"Adobe-Japan1","n":"CID+6407"},{"i":917761,"t":1,"c":"Hanyo-Denshi","n":"JA7262"},{"i":917761,"t":1,"c":"Moji_Joho","n":"MJ022295"},{"i":917762,"t":1,"c":"Hanyo-Denshi","n":"KS353720S"},{"i":917762,"t":1,"c":"Moji_Joho","n":"MJ022296"}]},"47":{"t":1,"n":"CJK UNIFIED IDEOGRAPH-8447","V":[{"i":917760,"t":1,"c":"Adobe-Japan1","n":"CID+22338"},{"i":917761,"t":1,"c":"Hanyo-Denshi","n":"JB5648"},{"i":917761,"t":1,"c":"Moji_Joho","n":"MJ022297"},{"i":917762,"t":1,"c":"Hanyo-Denshi","n":"KS353750"},{"i":917762,"t":1,"c":"Moji_Joho","n":"MJ022298"}]},"48":{"t":1,"n":"CJK UNIFIED IDEOGRAPH-8448","V":[{"i":917760,"t":1,"c":"Adobe-Japan1","n":"CID+8605"},{"i":917761,"t":1,"c":"Hanyo-Denshi","n":"JB5649"},{"i":917761,"t":1,"c":"Moji_Joho","n":"MJ022299"},{"i":917762,"t":1,"c":"Hanyo-Denshi","n":"KS353770"},{"i":917762,"t":1,"c":"Moji_Joho","n":"MJ022300"}]},"49":{"t":1,"n":"CJK UNIFIED IDEOGRAPH-8449","V":[{"i":65024,"t":2,"c":3,"n":"CJK COMPATIBILITY IDEOGRAPH-F96E"},{"i":917760,"t":1,"c":"Adobe-Japan1","n":"CID+3903"},{"i":917761,"t":1,"c":"Hanyo-Denshi","n":"JA4553"},{"i":917761,"t":1,"c":"Moji_Joho","n":"MJ022301"},{"i":917762,"t":1,"c":"Hanyo-Denshi","n":"JTB9DB"},{"i":917762,"t":1,"c":"Moji_Joho","n":"MJ022303"},{"i":917763,"t":1,"c":"Hanyo-Denshi","n":"JTB9DA"},{"i":917763,"t":1,"c":"Moji_Joho","n":"MJ022302"},{"i":917764,"t":1,"c":"Hanyo-Denshi","n":"TK01079740"}]},"4A":{"t":1,"n":"CJK UNIFIED IDEOGRAPH-844A","V":[{"i":917760,"t":1,"c":"Adobe-Japan1","n":"CID+15062"},{"i":917761,"t":1,"c":"Hanyo-Denshi","n":"JB5650"},{"i":917761,"t":1,"c":"Moji_Joho","n":"MJ022305"},{"i":917762,"t":1,"c":"Hanyo-Denshi","n":"JTB9F0"},{"i":917762,"t":1,"c":"Moji_Joho","n":"MJ022306"}]},"4D":{"t":1,"n":"CJK UNIFIED IDEOGRAPH-844D","V":[{"i":917760,"t":1,"c":"Adobe-Japan1","n":"CID+22339"},{"i":917761,"t":1,"c":"Hanyo-Denshi","n":"JB5651"},{"i":917761,"t":1,"c":"Moji_Joho","n":"MJ022309"},{"i":917762,"t":1,"c":"Hanyo-Denshi","n":"KS353860"},{"i":917762,"t":1,"c":"Moji_Joho","n":"MJ022310"}]},"4E":{"t":1,"n":"CJK UNIFIED IDEOGRAPH-844E","V":[{"i":917760,"t":1,"c":"Adobe-Japan1","n":"CID+3954"},{"i":917761,"t":1,"c":"Hanyo-Denshi","n":"JA4610"},{"i":917761,"t":1,"c":"Moji_Joho","n":"MJ022311"},{"i":917762,"t":1,"c":"Hanyo-Denshi","n":"KS353880"},{"i":917762,"t":1,"c":"Moji_Joho","n":"MJ022312"}]},"4F":{"t":1,"n":"CJK UNIFIED IDEOGRAPH-844F","V":[{"i":917760,"t":1,"c":"Adobe-Japan1","n":"CID+18509"},{"i":917761,"t":1,"c":"Hanyo-Denshi","n":"JB5652"},{"i":917761,"t":1,"c":"Moji_Joho","n":"MJ022313"},{"i":917762,"t":1,"c":"Hanyo-Denshi","n":"JTB9F2"},{"i":917762,"t":1,"c":"Moji_Joho","n":"MJ022314"}]},"51":{"t":1,"n":"CJK UNIFIED IDEOGRAPH-8451","V":[{"i":917760,"t":1,"c":"Adobe-Japan1","n":"CID+18510"},{"i":917761,"t":1,"c":"Hanyo-Denshi","n":"JB5653"},{"i":917761,"t":1,"c":"Moji_Joho","n":"MJ022316"},{"i":917762,"t":1,"c":"Hanyo-Denshi","n":"KS353900"},{"i":917762,"t":1,"c":"Moji_Joho","n":"MJ022317"}]},"52":{"t":1,"n":"CJK UNIFIED IDEOGRAPH-8452","V":[{"i":917760,"t":1,"c":"Adobe-Japan1","n":"CID+18511"},{"i":917761,"t":1,"c":"Hanyo-Denshi","n":"JB5654"},{"i":917761,"t":1,"c":"Moji_Joho","n":"MJ022318"},{"i":917762,"t":1,"c":"Hanyo-Denshi","n":"KS353920"},{"i":917762,"t":1,"c":"Moji_Joho","n":"MJ022319"}]},"55":{"t":1,"n":"CJK UNIFIED IDEOGRAPH-8455","V":[{"i":917760,"t":1,"c":"Hanyo-Denshi","n":"IP8455"},{"i":917761,"t":1,"c":"Hanyo-Denshi","n":"KS353960"}]},"56":{"t":1,"n":"CJK UNIFIED IDEOGRAPH-8456","V":[{"i":917760,"t":1,"c":"Adobe-Japan1","n":"CID+22340"},{"i":917761,"t":1,"c":"Hanyo-Denshi","n":"JB5655"},{"i":917761,"t":1,"c":"Moji_Joho","n":"MJ022324"},{"i":917762,"t":1,"c":"Hanyo-Denshi","n":"KS353990"},{"i":917762,"t":1,"c":"Moji_Joho","n":"MJ022325"}]},"57":{"t":1,"n":"CJK UNIFIED IDEOGRAPH-8457","V":[{"i":65024,"t":2,"c":3,"n":"CJK COMPATIBILITY IDEOGRAPH-FA5F"},{"i":65025,"t":2,"c":3,"n":"CJK COMPATIBILITY IDEOGRAPH-2F99F"},{"i":917760,"t":1,"c":"Adobe-Japan1","n":"CID+2998"},{"i":917761,"t":1,"c":"Adobe-Japan1","n":"CID+13367"},{"i":917762,"t":1,"c":"Hanyo-Denshi","n":"JA3588"},{"i":917762,"t":1,"c":"Moji_Joho","n":"MJ022326"},{"i":917763,"t":1,"c":"Hanyo-Denshi","n":"KS354000"},{"i":917763,"t":1,"c":"Moji_Joho","n":"MJ022327"},{"i":917764,"t":1,"c":"Hanyo-Denshi","n":"JC9107"},{"i":917764,"t":1,"c":"Moji_Joho","n":"MJ030294"}]},"58":{"t":1,"n":"CJK UNIFIED IDEOGRAPH-8458","V":[{"i":917760,"t":1,"c":"Adobe-Japan1","n":"CID+19743"},{"i":917761,"t":1,"c":"Hanyo-Denshi","n":"JB5656"},{"i":917761,"t":1,"c":"Moji_Joho","n":"MJ022328"},{"i":917762,"t":1,"c":"Hanyo-Denshi","n":"KS354030"},{"i":917762,"t":1,"c":"Moji_Joho","n":"MJ022329"}]},"59":{"t":1,"n":"CJK UNIFIED IDEOGRAPH-8459","V":[{"i":917760,"t":1,"c":"Adobe-Japan1","n":"CID+18512"},{"i":917761,"t":1,"c":"Hanyo-Denshi","n":"JB5657"},{"i":917761,"t":1,"c":"Moji_Joho","n":"MJ022330"},{"i":917762,"t":1,"c":"Hanyo-Denshi","n":"KS354040"},{"i":917762,"t":1,"c":"Moji_Joho","n":"MJ022331"}]},"5A":{"t":1,"n":"CJK UNIFIED IDEOGRAPH-845A","V":[{"i":917760,"t":1,"c":"Adobe-Japan1","n":"CID+18513"},{"i":917761,"t":1,"c":"Hanyo-Denshi","n":"JB5658"},{"i":917761,"t":1,"c":"Moji_Joho","n":"MJ022332"},{"i":917762,"t":1,"c":"Hanyo-Denshi","n":"KS354060"},{"i":917762,"t":1,"c":"Moji_Joho","n":"MJ022333"},{"i":917763,"t":1,"c":"Hanyo-Denshi","n":"KS356080S"},{"i":917763,"t":1,"c":"Moji_Joho","n":"MJ022334"}]},"5B":{"t":1,"n":"CJK UNIFIED IDEOGRAPH-845B","V":[{"i":917760,"t":1,"c":"Adobe-Japan1","n":"CID+1481"},{"i":917761,"t":1,"c":"Adobe-Japan1","n":"CID+7652"},{"i":917762,"t":1,"c":"Hanyo-Denshi","n":"JA1975"},{"i":917762,"t":1,"c":"Moji_Joho","n":"MJ022335"},{"i":917763,"t":1,"c":"Hanyo-Denshi","n":"FT1769"},{"i":917763,"t":1,"c":"Moji_Joho","n":"MJ022336"},{"i":917764,"t":1,"c":"Hanyo-Denshi","n":"JTB9D7"},{"i":917764,"t":1,"c":"Moji_Joho","n":"MJ022340"},{"i":917765,"t":1,"c":"Hanyo-Denshi","n":"JTB9D8"},{"i":917765,"t":1,"c":"Moji_Joho","n":"MJ022341"},{"i":917766,"t":1,"c":"Hanyo-Denshi","n":"JTB9D6"},{"i":917766,"t":1,"c":"Moji_Joho","n":"MJ022338"},{"i":917767,"t":1,"c":"Hanyo-Denshi","n":"KS352870"},{"i":917767,"t":1,"c":"Moji_Joho","n":"MJ022337"},{"i":917768,"t":1,"c":"Hanyo-Denshi","n":"JTC0F7"},{"i":917768,"t":1,"c":"Moji_Joho","n":"MJ022339"},{"i":917769,"t":1,"c":"Hanyo-Denshi","n":"TK01079040"}]},"5C":{"t":1,"n":"CJK UNIFIED IDEOGRAPH-845C","V":[{"i":917760,"t":1,"c":"Adobe-Japan1","n":"CID+18514"},{"i":917761,"t":1,"c":"Adobe-Japan1","n":"CID+22341"},{"i":917762,"t":1,"c":"Hanyo-Denshi","n":"JB5659"},{"i":917762,"t":1,"c":"Moji_Joho","n":"MJ022342"},{"i":917763,"t":1,"c":"Hanyo-Denshi","n":"KS354100"},{"i":917763,"t":1,"c":"Moji_Joho","n":"MJ022343"},{"i":917764,"t":1,"c":"Hanyo-Denshi","n":"JD8645"},{"i":917764,"t":1,"c":"Moji_Joho","n":"MJ022344"}]},"5F":{"t":1,"n":"CJK UNIFIED IDEOGRAPH-845F","V":[{"i":917760,"t":1,"c":"Adobe-Japan1","n":"CID+17083"},{"i":917761,"t":1,"c":"Hanyo-Denshi","n":"JC9109"},{"i":917761,"t":1,"c":"Moji_Joho","n":"MJ022347"},{"i":917762,"t":1,"c":"Hanyo-Denshi","n":"JTB9F3"},{"i":917762,"t":1,"c":"Moji_Joho","n":"MJ022348"}]},"60":{"t":1,"n":"CJK UNIFIED IDEOGRAPH-8460","V":[{"i":917760,"t":1,"c":"Adobe-Japan1","n":"CID+22342"},{"i":917761,"t":1,"c":"Hanyo-Denshi","n":"JB5660"},{"i":917761,"t":1,"c":"Moji_Joho","n":"MJ022349"},{"i":917762,"t":1,"c":"Hanyo-Denshi","n":"KS354170"},{"i":917762,"t":1,"c":"Moji_Joho","n":"MJ022350"}]},"61":{"t":1,"n":"CJK UNIFIED IDEOGRAPH-8461","V":[{"i":917760,"t":1,"c":"Adobe-Japan1","n":"CID+3556"},{"i":917761,"t":1,"c":"Hanyo-Denshi","n":"JA4182"},{"i":917761,"t":1,"c":"Moji_Joho","n":"MJ022351"},{"i":917762,"t":1,"c":"Hanyo-Denshi","n":"KS354190"},{"i":917762,"t":1,"c":"Moji_Joho","n":"MJ022352"}]},"62":{"t":1,"n":"CJK UNIFIED IDEOGRAPH-8462","V":[{"i":917760,"t":1,"c":"Adobe-Japan1","n":"CID+6413"},{"i":917761,"t":1,"c":"Hanyo-Denshi","n":"JA7268"},{"i":917761,"t":1,"c":"Moji_Joho","n":"MJ022353"},{"i":917762,"t":1,"c":"Hanyo-Denshi","n":"KS356070"},{"i":917762,"t":1,"c":"Moji_Joho","n":"MJ022355"},{"i":917763,"t":1,"c":"Hanyo-Denshi","n":"KS354210"},{"i":917763,"t":1,"c":"Moji_Joho","n":"MJ022354"}]},"63":{"t":1,"n":"CJK UNIFIED IDEOGRAPH-8463","V":[{"i":917760,"t":1,"c":"Adobe-Japan1","n":"CID+3193"},{"i":917761,"t":1,"c":"Hanyo-Denshi","n":"JA3801"},{"i":917761,"t":1,"c":"Moji_Joho","n":"MJ022356"},{"i":917762,"t":1,"c":"Hanyo-Denshi","n":"JTB9EF"},{"i":917762,"t":1,"c":"Moji_Joho","n":"MJ022357"},{"i":917763,"t":1,"c":"Hanyo-Denshi","n":"TK01080030"}]},"64":{"t":1,"n":"CJK UNIFIED IDEOGRAPH-8464","V":[{"i":917760,"t":1,"c":"Adobe-Japan1","n":"CID+22343"},{"i":917761,"t":1,"c":"Hanyo-Denshi","n":"JB5661"},{"i":917761,"t":1,"c":"Moji_Joho","n":"MJ022359"},{"i":917762,"t":1,"c":"Hanyo-Denshi","n":"KS354240"},{"i":917762,"t":1,"c":"Moji_Joho","n":"MJ022360"}]},"65":{"t":1,"n":"CJK UNIFIED IDEOGRAPH-8465","V":[{"i":917760,"t":1,"c":"Adobe-Japan1","n":"CID+18516"},{"i":917761,"t":1,"c":"Hanyo-Denshi","n":"JB5662"},{"i":917761,"t":1,"c":"Moji_Joho","n":"MJ022361"},{"i":917762,"t":1,"c":"Hanyo-Denshi","n":"KS354250"},{"i":917762,"t":1,"c":"Moji_Joho","n":"MJ022362"}]},"66":{"t":1,"n":"CJK UNIFIED IDEOGRAPH-8466","V":[{"i":917760,"t":1,"c":"Adobe-Japan1","n":"CID+1141"},{"i":917761,"t":1,"c":"Hanyo-Denshi","n":"JA1617"},{"i":917761,"t":1,"c":"Moji_Joho","n":"MJ022364"},{"i":917762,"t":1,"c":"Hanyo-Denshi","n":"KS356060"},{"i":917762,"t":1,"c":"Moji_Joho","n":"MJ022365"},{"i":917763,"t":1,"c":"Hanyo-Denshi","n":"JTBA09"},{"i":917763,"t":1,"c":"Moji_Joho","n":"MJ022368"},{"i":917764,"t":1,"c":"Hanyo-Denshi","n":"JTB9E3S"},{"i":917764,"t":1,"c":"Moji_Joho","n":"MJ022366"},{"i":917765,"t":1,"c":"Moji_Joho","n":"MJ022363"},{"i":917766,"t":1,"c":"Moji_Joho","n":"MJ022367"}]},"67":{"t":1,"n":"CJK UNIFIED IDEOGRAPH-8467","V":[{"i":917760,"t":1,"c":"Adobe-Japan1","n":"CID+22344"},{"i":917761,"t":1,"c":"Hanyo-Denshi","n":"JB5663"},{"i":917761,"t":1,"c":"Moji_Joho","n":"MJ022369"},{"i":917762,"t":1,"c":"Hanyo-Denshi","n":"KS354270"},{"i":917762,"t":1,"c":"Moji_Joho","n":"MJ022370"}]},"69":{"t":1,"n":"CJK UNIFIED IDEOGRAPH-8469","V":[{"i":917760,"t":1,"c":"Adobe-Japan1","n":"CID+6406"},{"i":917761,"t":1,"c":"Hanyo-Denshi","n":"JA7261"},{"i":917761,"t":1,"c":"Moji_Joho","n":"MJ022372"},{"i":917762,"t":1,"c":"Hanyo-Denshi","n":"KS354300"},{"i":917762,"t":1,"c":"Moji_Joho","n":"MJ022373"}]},"6A":{"t":1,"n":"CJK UNIFIED IDEOGRAPH-846A","V":[{"i":917760,"t":1,"c":"Adobe-Japan1","n":"CID+22345"},{"i":917761,"t":1,"c":"Hanyo-Denshi","n":"JB5664"},{"i":917761,"t":1,"c":"Moji_Joho","n":"MJ022374"},{"i":917762,"t":1,"c":"Hanyo-Denshi","n":"KS354310"},{"i":917762,"t":1,"c":"Moji_Joho","n":"MJ022375"}]},"6B":{"t":1,"n":"CJK UNIFIED IDEOGRAPH-846B","V":[{"i":917760,"t":1,"c":"Adobe-Japan1","n":"CID+6402"},{"i":917761,"t":1,"c":"Hanyo-Denshi","n":"JA7257"},{"i":917761,"t":1,"c":"Moji_Joho","n":"MJ022376"},{"i":917762,"t":1,"c":"Hanyo-Denshi","n":"KS354320"},{"i":917762,"t":1,"c":"Moji_Joho","n":"MJ022377"}]},"6C":{"t":1,"n":"CJK UNIFIED IDEOGRAPH-846C","V":[{"i":917760,"t":1,"c":"Adobe-Japan1","n":"CID+2804"},{"i":917761,"t":1,"c":"Hanyo-Denshi","n":"JA3382"},{"i":917761,"t":1,"c":"Moji_Joho","n":"MJ022378"},{"i":917762,"t":1,"c":"Hanyo-Denshi","n":"KS354370"},{"i":917762,"t":1,"c":"Moji_Joho","n":"MJ022379"}]},"6D":{"t":1,"n":"CJK UNIFIED IDEOGRAPH-846D","V":[{"i":917760,"t":1,"c":"Adobe-Japan1","n":"CID+6396"},{"i":917761,"t":1,"c":"Hanyo-Denshi","n":"JA7251"},{"i":917761,"t":1,"c":"Moji_Joho","n":"MJ022380"},{"i":917762,"t":1,"c":"Hanyo-Denshi","n":"JTB9EB"},{"i":917762,"t":1,"c":"Moji_Joho","n":"MJ022381"}]},"6E":{"t":1,"n":"CJK UNIFIED IDEOGRAPH-846E","V":[{"i":917760,"t":1,"c":"Adobe-Japan1","n":"CID+6404"},{"i":917761,"t":1,"c":"Hanyo-Denshi","n":"JA7259"},{"i":917761,"t":1,"c":"Moji_Joho","n":"MJ022382"},{"i":917762,"t":1,"c":"Hanyo-Denshi","n":"KS354390"},{"i":917762,"t":1,"c":"Moji_Joho","n":"MJ022383"}]},"6F":{"t":1,"n":"CJK UNIFIED IDEOGRAPH-846F","V":[{"i":917760,"t":1,"c":"Adobe-Japan1","n":"CID+6409"},{"i":917761,"t":1,"c":"Hanyo-Denshi","n":"JA7264"},{"i":917761,"t":1,"c":"Moji_Joho","n":"MJ022384"},{"i":917762,"t":1,"c":"Hanyo-Denshi","n":"KS354400"},{"i":917762,"t":1,"c":"Moji_Joho","n":"MJ022385"}]},"70":{"t":1,"n":"CJK UNIFIED IDEOGRAPH-8470","V":[{"i":917760,"t":1,"c":"Adobe-Japan1","n":"CID+17084"},{"i":917761,"t":1,"c":"Hanyo-Denshi","n":"JB5665"},{"i":917761,"t":1,"c":"Moji_Joho","n":"MJ022386"},{"i":917762,"t":1,"c":"Hanyo-Denshi","n":"KS354420"},{"i":917762,"t":1,"c":"Moji_Joho","n":"MJ022387"}]},"71":{"t":1,"n":"CJK UNIFIED IDEOGRAPH-8471","V":[{"i":917760,"t":1,"c":"Adobe-Japan1","n":"CID+3298"},{"i":917761,"t":1,"c":"Hanyo-Denshi","n":"JA3912"},{"i":917761,"t":1,"c":"Moji_Joho","n":"MJ022388"},{"i":917762,"t":1,"c":"Hanyo-Denshi","n":"KS354430S"},{"i":917762,"t":1,"c":"Moji_Joho","n":"MJ022389"}]},"73":{"t":1,"n":"CJK UNIFIED IDEOGRAPH-8473","V":[{"i":917760,"t":1,"c":"Adobe-Japan1","n":"CID+17085"},{"i":917761,"t":1,"c":"Hanyo-Denshi","n":"JB5666"},{"i":917761,"t":1,"c":"Moji_Joho","n":"MJ022391"},{"i":917762,"t":1,"c":"Hanyo-Denshi","n":"JTB9F6"},{"i":917762,"t":1,"c":"Moji_Joho","n":"MJ022392"}]},"74":{"t":1,"n":"CJK UNIFIED IDEOGRAPH-8474","V":[{"i":917760,"t":1,"c":"Adobe-Japan1","n":"CID+22346"},{"i":917761,"t":1,"c":"Hanyo-Denshi","n":"JB5667"},{"i":917761,"t":1,"c":"Moji_Joho","n":"MJ022393"},{"i":917762,"t":1,"c":"Hanyo-Denshi","n":"KS354460"},{"i":917762,"t":1,"c":"Moji_Joho","n":"MJ022394"}]},"75":{"t":1,"n":"CJK UNIFIED IDEOGRAPH-8475","V":[{"i":917760,"t":1,"c":"Adobe-Japan1","n":"CID+1134"},{"i":917761,"t":1,"c":"Hanyo-Denshi","n":"JA1610"},{"i":917761,"t":1,"c":"Moji_Joho","n":"MJ022395"},{"i":917762,"t":1,"c":"Hanyo-Denshi","n":"JTB9F7"},{"i":917762,"t":1,"c":"Moji_Joho","n":"MJ022396"}]},"76":{"t":1,"n":"CJK UNIFIED IDEOGRAPH-8476","V":[{"i":917760,"t":1,"c":"Adobe-Japan1","n":"CID+15063"},{"i":917761,"t":1,"c":"Hanyo-Denshi","n":"JB5668"},{"i":917761,"t":1,"c":"Moji_Joho","n":"MJ022397"},{"i":917762,"t":1,"c":"Hanyo-Denshi","n":"KS354480"},{"i":917762,"t":1,"c":"Moji_Joho","n":"MJ022398"}]},"77":{"t":1,"n":"CJK UNIFIED IDEOGRAPH-8477","V":[{"i":917760,"t":1,"c":"Adobe-Japan1","n":"CID+6401"},{"i":917761,"t":1,"c":"Hanyo-Denshi","n":"JA7256"},{"i":917761,"t":1,"c":"Moji_Joho","n":"MJ022399"},{"i":917762,"t":1,"c":"Hanyo-Denshi","n":"KS354490"},{"i":917762,"t":1,"c":"Moji_Joho","n":"MJ022400"}]},"78":{"t":1,"n":"CJK UNIFIED IDEOGRAPH-8478","V":[{"i":917760,"t":1,"c":"Adobe-Japan1","n":"CID+18517"},{"i":917761,"t":1,"c":"Hanyo-Denshi","n":"JB5669"},{"i":917761,"t":1,"c":"Moji_Joho","n":"MJ022401"},{"i":917762,"t":1,"c":"Hanyo-Denshi","n":"JTB9F8"},{"i":917762,"t":1,"c":"Moji_Joho","n":"MJ022402"}]},"79":{"t":1,"n":"CJK UNIFIED IDEOGRAPH-8479","V":[{"i":917760,"t":1,"c":"Adobe-Japan1","n":"CID+6410"},{"i":917761,"t":1,"c":"Hanyo-Denshi","n":"JA7265"},{"i":917761,"t":1,"c":"Moji_Joho","n":"MJ022403"},{"i":917762,"t":1,"c":"Hanyo-Denshi","n":"KS354520S"},{"i":917762,"t":1,"c":"Moji_Joho","n":"MJ022404"}]},"7A":{"t":1,"n":"CJK UNIFIED IDEOGRAPH-847A","V":[{"i":917760,"t":1,"c":"Adobe-Japan1","n":"CID+3562"},{"i":917761,"t":1,"c":"Adobe-Japan1","n":"CID+13498"},{"i":917762,"t":1,"c":"Hanyo-Denshi","n":"JA4188"},{"i":917762,"t":1,"c":"Moji_Joho","n":"MJ022405"},{"i":917763,"t":1,"c":"Hanyo-Denshi","n":"KS354530"},{"i":917763,"t":1,"c":"Moji_Joho","n":"MJ022406"},{"i":917764,"t":1,"c":"Moji_Joho","n":"MJ022407"}]},"7B":{"t":1,"n":"CJK UNIFIED IDEOGRAPH-847B","V":[{"i":917760,"t":1,"c":"Hanyo-Denshi","n":"IP847B"},{"i":917760,"t":1,"c":"Moji_Joho","n":"MJ022408"},{"i":917761,"t":1,"c":"Hanyo-Denshi","n":"KS354540"},{"i":917761,"t":1,"c":"Moji_Joho","n":"MJ022409"}]},"7C":{"t":1,"n":"CJK UNIFIED IDEOGRAPH-847C","V":[{"i":917760,"t":1,"c":"Adobe-Japan1","n":"CID+18518"},{"i":917761,"t":1,"c":"Hanyo-Denshi","n":"JB5670"},{"i":917761,"t":1,"c":"Moji_Joho","n":"MJ022410"},{"i":917762,"t":1,"c":"Hanyo-Denshi","n":"KS356040"},{"i":917762,"t":1,"c":"Moji_Joho","n":"MJ022411"}]},"7D":{"t":1,"n":"CJK UNIFIED IDEOGRAPH-847D","V":[{"i":917760,"t":1,"c":"Adobe-Japan1","n":"CID+22347"},{"i":917761,"t":1,"c":"Hanyo-Denshi","n":"JB5671"},{"i":917761,"t":1,"c":"Moji_Joho","n":"MJ022412"},{"i":917762,"t":1,"c":"Hanyo-Denshi","n":"JTB9F5"},{"i":917762,"t":1,"c":"Moji_Joho","n":"MJ022415"},{"i":917763,"t":1,"c":"Hanyo-Denshi","n":"KS352940"},{"i":917763,"t":1,"c":"Moji_Joho","n":"MJ022413"},{"i":917764,"t":1,"c":"Hanyo-Denshi","n":"KS354550"},{"i":917764,"t":1,"c":"Moji_Joho","n":"MJ022414"}]},"80":{"t":1,"n":"CJK UNIFIED IDEOGRAPH-8480","V":[{"i":917760,"t":1,"c":"Hanyo-Denshi","n":"IP8480"},{"i":917761,"t":1,"c":"Hanyo-Denshi","n":"KS354630"}]},"81":{"t":1,"n":"CJK UNIFIED IDEOGRAPH-8481","V":[{"i":917760,"t":1,"c":"Adobe-Japan1","n":"CID+18519"},{"i":917761,"t":1,"c":"Hanyo-Denshi","n":"JB5672"},{"i":917761,"t":1,"c":"Moji_Joho","n":"MJ022421"},{"i":917762,"t":1,"c":"Hanyo-Denshi","n":"KS356030"},{"i":917762,"t":1,"c":"Moji_Joho","n":"MJ022423"},{"i":917763,"t":1,"c":"Hanyo-Denshi","n":"IB0864"},{"i":917763,"t":1,"c":"Moji_Joho","n":"MJ022420"},{"i":917764,"t":1,"c":"Hanyo-Denshi","n":"KS354640"},{"i":917764,"t":1,"c":"Moji_Joho","n":"MJ022422"}]},"82":{"t":1,"n":"CJK UNIFIED IDEOGRAPH-8482","V":[{"i":917760,"t":1,"c":"Adobe-Japan1","n":"CID+6405"},{"i":917761,"t":1,"c":"Hanyo-Denshi","n":"JA7260"},{"i":917761,"t":1,"c":"Moji_Joho","n":"MJ022424"},{"i":917762,"t":1,"c":"Hanyo-Denshi","n":"KS355980"},{"i":917762,"t":1,"c":"Moji_Joho","n":"MJ022426"},{"i":917763,"t":1,"c":"Hanyo-Denshi","n":"KS354820S"},{"i":917763,"t":1,"c":"Moji_Joho","n":"MJ022425"}]},"84":{"t":1,"n":"CJK UNIFIED IDEOGRAPH-8484","V":[{"i":917760,"t":1,"c":"Adobe-Japan1","n":"CID+6400"},{"i":917761,"t":1,"c":"Hanyo-Denshi","n":"JA7255"},{"i":917761,"t":1,"c":"Moji_Joho","n":"MJ022428"},{"i":917762,"t":1,"c":"Hanyo-Denshi","n":"JTB9F1S"},{"i":917762,"t":1,"c":"Moji_Joho","n":"MJ022429"}]},"85":{"t":1,"n":"CJK UNIFIED IDEOGRAPH-8485","V":[{"i":917760,"t":1,"c":"Adobe-Japan1","n":"CID+17086"},{"i":917761,"t":1,"c":"Hanyo-Denshi","n":"JB5673"},{"i":917761,"t":1,"c":"Moji_Joho","n":"MJ022430"},{"i":917762,"t":1,"c":"Hanyo-Denshi","n":"KS355150"},{"i":917762,"t":1,"c":"Moji_Joho","n":"MJ022431"},{"i":917763,"t":1,"c":"Hanyo-Denshi","n":"JTBA0E"},{"i":917763,"t":1,"c":"Moji_Joho","n":"MJ022432"}]},"8B":{"t":1,"n":"CJK UNIFIED IDEOGRAPH-848B","V":[{"i":917760,"t":1,"c":"Adobe-Japan1","n":"CID+2493"},{"i":917761,"t":1,"c":"Hanyo-Denshi","n":"JA3053"},{"i":917761,"t":1,"c":"Moji_Joho","n":"MJ022433"},{"i":917762,"t":1,"c":"Hanyo-Denshi","n":"JTBA07"},{"i":917762,"t":1,"c":"Moji_Joho","n":"MJ022434"},{"i":917763,"t":1,"c":"Hanyo-Denshi","n":"TK01079380"},{"i":917764,"t":1,"c":"Hanyo-Denshi","n":"TK01079600"}]},"90":{"t":1,"n":"CJK UNIFIED IDEOGRAPH-8490","V":[{"i":917760,"t":1,"c":"Adobe-Japan1","n":"CID+2361"},{"i":917761,"t":1,"c":"Hanyo-Denshi","n":"JA2915"},{"i":917761,"t":1,"c":"Moji_Joho","n":"MJ022437"},{"i":917762,"t":1,"c":"Hanyo-Denshi","n":"KS356210"},{"i":917762,"t":1,"c":"Moji_Joho","n":"MJ022438"}]},"92":{"t":1,"n":"CJK UNIFIED IDEOGRAPH-8492","V":[{"i":917760,"t":1,"c":"Adobe-Japan1","n":"CID+22348"},{"i":917761,"t":1,"c":"Hanyo-Denshi","n":"JB5674"},{"i":917761,"t":1,"c":"Moji_Joho","n":"MJ022440"},{"i":917762,"t":1,"c":"Hanyo-Denshi","n":"KS356260"},{"i":917762,"t":1,"c":"Moji_Joho","n":"MJ022441"}]},"93":{"t":1,"n":"CJK UNIFIED IDEOGRAPH-8493","V":[{"i":917760,"t":1,"c":"Adobe-Japan1","n":"CID+19744"},{"i":917761,"t":1,"c":"Hanyo-Denshi","n":"JB5675"},{"i":917761,"t":1,"c":"Moji_Joho","n":"MJ022442"},{"i":917762,"t":1,"c":"Hanyo-Denshi","n":"KS356270"},{"i":917762,"t":1,"c":"Moji_Joho","n":"MJ022443"}]},"94":{"t":1,"n":"CJK UNIFIED IDEOGRAPH-8494","V":[{"i":917760,"t":1,"c":"Adobe-Japan1","n":"CID+2264"},{"i":917761,"t":1,"c":"Hanyo-Denshi","n":"JA2812"},{"i":917761,"t":1,"c":"Moji_Joho","n":"MJ022444"},{"i":917762,"t":1,"c":"Hanyo-Denshi","n":"KS356280"},{"i":917762,"t":1,"c":"Moji_Joho","n":"MJ022445"}]},"95":{"t":1,"n":"CJK UNIFIED IDEOGRAPH-8495","V":[{"i":917760,"t":1,"c":"Adobe-Japan1","n":"CID+22349"},{"i":917761,"t":1,"c":"Hanyo-Denshi","n":"JB5676"},{"i":917761,"t":1,"c":"Moji_Joho","n":"MJ022446"},{"i":917762,"t":1,"c":"Hanyo-Denshi","n":"KS356290"},{"i":917762,"t":1,"c":"Moji_Joho","n":"MJ022447"}]},"97":{"t":1,"n":"CJK UNIFIED IDEOGRAPH-8497","V":[{"i":917760,"t":1,"c":"Adobe-Japan1","n":"CID+18521"},{"i":917761,"t":1,"c":"Hanyo-Denshi","n":"JD8654"},{"i":917761,"t":1,"c":"Moji_Joho","n":"MJ022449"},{"i":917762,"t":1,"c":"Hanyo-Denshi","n":"KS356330"},{"i":917762,"t":1,"c":"Moji_Joho","n":"MJ022450"}]},"99":{"t":1,"n":"CJK UNIFIED IDEOGRAPH-8499","V":[{"i":917760,"t":1,"c":"Adobe-Japan1","n":"CID+3812"},{"i":917761,"t":1,"c":"Hanyo-Denshi","n":"JA4456"},{"i":917761,"t":1,"c":"Moji_Joho","n":"MJ022452"},{"i":917762,"t":1,"c":"Hanyo-Denshi","n":"KS356360"},{"i":917762,"t":1,"c":"Moji_Joho","n":"MJ022453"},{"i":917763,"t":1,"c":"Hanyo-Denshi","n":"FT2056"},{"i":917763,"t":1,"c":"Moji_Joho","n":"MJ022454"},{"i":917764,"t":1,"c":"Hanyo-Denshi","n":"JTBBB7"},{"i":917764,"t":1,"c":"Moji_Joho","n":"MJ022455"}]},"9C":{"t":1,"n":"CJK UNIFIED IDEOGRAPH-849C","V":[{"i":917760,"t":1,"c":"Adobe-Japan1","n":"CID+3513"},{"i":917761,"t":1,"c":"Hanyo-Denshi","n":"JA4139"},{"i":917761,"t":1,"c":"Moji_Joho","n":"MJ022459"},{"i":917762,"t":1,"c":"Hanyo-Denshi","n":"IB0359"},{"i":917762,"t":1,"c":"Moji_Joho","n":"MJ022460"},{"i":917763,"t":1,"c":"Hanyo-Denshi","n":"JTB9D4"},{"i":917763,"t":1,"c":"Moji_Joho","n":"MJ022458"}]},"9D":{"t":1,"n":"CJK UNIFIED IDEOGRAPH-849D","V":[{"i":917760,"t":1,"c":"Hanyo-Denshi","n":"KS356450"},{"i":917761,"t":1,"c":"Hanyo-Denshi","n":"TK01079880"}]},"9E":{"t":1,"n":"CJK UNIFIED IDEOGRAPH-849E","V":[{"i":917760,"t":1,"c":"Adobe-Japan1","n":"CID+17087"},{"i":917761,"t":1,"c":"Hanyo-Denshi","n":"JB5677"},{"i":917761,"t":1,"c":"Moji_Joho","n":"MJ022463"},{"i":917762,"t":1,"c":"Hanyo-Denshi","n":"JTBA17"},{"i":917762,"t":1,"c":"Moji_Joho","n":"MJ022464"}]},"9F":{"t":1,"n":"CJK UNIFIED IDEOGRAPH-849F","V":[{"i":917760,"t":1,"c":"Adobe-Japan1","n":"CID+6416"},{"i":917761,"t":1,"c":"Hanyo-Denshi","n":"JA7271"},{"i":917761,"t":1,"c":"Moji_Joho","n":"MJ022465"},{"i":917762,"t":1,"c":"Hanyo-Denshi","n":"KS356470"},{"i":917762,"t":1,"c":"Moji_Joho","n":"MJ022466"}]},"A1":{"t":1,"n":"CJK UNIFIED IDEOGRAPH-84A1","V":[{"i":917760,"t":1,"c":"Adobe-Japan1","n":"CID+6425"},{"i":917761,"t":1,"c":"Hanyo-Denshi","n":"JA7280"},{"i":917761,"t":1,"c":"Moji_Joho","n":"MJ022468"},{"i":917762,"t":1,"c":"Hanyo-Denshi","n":"KS358510"},{"i":917762,"t":1,"c":"Moji_Joho","n":"MJ022470"},{"i":917763,"t":1,"c":"Hanyo-Denshi","n":"KS356530"},{"i":917763,"t":1,"c":"Moji_Joho","n":"MJ022469"}]},"A5":{"t":1,"n":"CJK UNIFIED IDEOGRAPH-84A5","V":[{"i":917760,"t":1,"c":"Hanyo-Denshi","n":"KS356580"},{"i":917761,"t":1,"c":"Hanyo-Denshi","n":"TK01079890"}]},"A6":{"t":1,"n":"CJK UNIFIED IDEOGRAPH-84A6","V":[{"i":917760,"t":1,"c":"Adobe-Japan1","n":"CID+18522"},{"i":917761,"t":1,"c":"Hanyo-Denshi","n":"JB5678"},{"i":917761,"t":1,"c":"Moji_Joho","n":"MJ022475"},{"i":917762,"t":1,"c":"Hanyo-Denshi","n":"JTBA16"},{"i":917762,"t":1,"c":"Moji_Joho","n":"MJ022477"},{"i":917763,"t":1,"c":"Hanyo-Denshi","n":"JTBA15"},{"i":917763,"t":1,"c":"Moji_Joho","n":"MJ022476"}]},"A7":{"t":1,"n":"CJK UNIFIED IDEOGRAPH-84A7","V":[{"i":917760,"t":1,"c":"Hanyo-Denshi","n":"KS355780"},{"i":917760,"t":1,"c":"Moji_Joho","n":"MJ022478"},{"i":917761,"t":1,"c":"Hanyo-Denshi","n":"KS358560"},{"i":917761,"t":1,"c":"Moji_Joho","n":"MJ022479"}]},"A8":{"t":1,"n":"CJK UNIFIED IDEOGRAPH-84A8","V":[{"i":917760,"t":1,"c":"Adobe-Japan1","n":"CID+15064"},{"i":917761,"t":1,"c":"Hanyo-Denshi","n":"JB5679"},{"i":917761,"t":1,"c":"Moji_Joho","n":"MJ022480"},{"i":917762,"t":1,"c":"Hanyo-Denshi","n":"IB0358"},{"i":917762,"t":1,"c":"Moji_Joho","n":"MJ022482"},{"i":917763,"t":1,"c":"Hanyo-Denshi","n":"IB0865"},{"i":917763,"t":1,"c":"Moji_Joho","n":"MJ022481"},{"i":917764,"t":1,"c":"Hanyo-Denshi","n":"TK01080090"}]},"A9":{"t":1,"n":"CJK UNIFIED IDEOGRAPH-84A9","V":[{"i":917760,"t":1,"c":"Adobe-Japan1","n":"CID+22350"},{"i":917761,"t":1,"c":"Hanyo-Denshi","n":"JB5680"},{"i":917761,"t":1,"c":"Moji_Joho","n":"MJ022484"},{"i":917762,"t":1,"c":"Hanyo-Denshi","n":"KS356720"},{"i":917762,"t":1,"c":"Moji_Joho","n":"MJ022485"}]},"AA":{"t":1,"n":"CJK UNIFIED IDEOGRAPH-84AA","V":[{"i":917760,"t":1,"c":"Adobe-Japan1","n":"CID+22351"},{"i":917761,"t":1,"c":"Hanyo-Denshi","n":"JB5681"},{"i":917761,"t":1,"c":"Moji_Joho","n":"MJ022486"},{"i":917762,"t":1,"c":"Hanyo-Denshi","n":"KS356730"},{"i":917762,"t":1,"c":"Moji_Joho","n":"MJ022487"}]},"AD":{"t":1,"n":"CJK UNIFIED IDEOGRAPH-84AD","V":[{"i":917760,"t":1,"c":"Adobe-Japan1","n":"CID+6403"},{"i":917761,"t":1,"c":"Hanyo-Denshi","n":"JA7258"},{"i":917761,"t":1,"c":"Moji_Joho","n":"MJ022490"},{"i":917762,"t":1,"c":"Hanyo-Denshi","n":"KS356770"},{"i":917762,"t":1,"c":"Moji_Joho","n":"MJ022491"}]},"AF":{"t":1,"n":"CJK UNIFIED IDEOGRAPH-84AF","V":[{"i":917760,"t":1,"c":"Adobe-Japan1","n":"CID+15065"},{"i":917761,"t":1,"c":"Hanyo-Denshi","n":"JB5682"},{"i":917761,"t":1,"c":"Moji_Joho","n":"MJ022493"},{"i":917762,"t":1,"c":"Hanyo-Denshi","n":"KS356800"},{"i":917762,"t":1,"c":"Moji_Joho","n":"MJ022494"}]},"B1":{"t":1,"n":"CJK UNIFIED IDEOGRAPH-84B1","V":[{"i":917760,"t":1,"c":"Adobe-Japan1","n":"CID+19745"},{"i":917761,"t":1,"c":"Hanyo-Denshi","n":"JB5683"},{"i":917761,"t":1,"c":"Moji_Joho","n":"MJ022496"},{"i":917762,"t":1,"c":"Hanyo-Denshi","n":"KS356890"},{"i":917762,"t":1,"c":"Moji_Joho","n":"MJ022497"}]},"B2":{"t":1,"n":"CJK UNIFIED IDEOGRAPH-84B2","V":[{"i":917760,"t":1,"c":"Adobe-Japan1","n":"CID+1493"},{"i":917761,"t":1,"c":"Hanyo-Denshi","n":"JA1987"},{"i":917761,"t":1,"c":"Moji_Joho","n":"MJ022498"},{"i":917762,"t":1,"c":"Hanyo-Denshi","n":"JTBA14"},{"i":917762,"t":1,"c":"Moji_Joho","n":"MJ022499"},{"i":917763,"t":1,"c":"Hanyo-Denshi","n":"TK01078940"}]},"B4":{"t":1,"n":"CJK UNIFIED IDEOGRAPH-84B4","V":[{"i":917760,"t":1,"c":"Adobe-Japan1","n":"CID+8606"},{"i":917761,"t":1,"c":"Hanyo-Denshi","n":"JB5684"},{"i":917761,"t":1,"c":"Moji_Joho","n":"MJ022501"},{"i":917762,"t":1,"c":"Hanyo-Denshi","n":"KS356930"},{"i":917762,"t":1,"c":"Moji_Joho","n":"MJ022502"}]},"B8":{"t":1,"n":"CJK UNIFIED IDEOGRAPH-84B8","V":[{"i":917760,"t":1,"c":"Adobe-Japan1","n":"CID+2528"},{"i":917761,"t":1,"c":"Hanyo-Denshi","n":"JA3088"},{"i":917761,"t":1,"c":"Moji_Joho","n":"MJ022506"},{"i":917762,"t":1,"c":"Hanyo-Denshi","n":"KS356970"},{"i":917762,"t":1,"c":"Moji_Joho","n":"MJ022507"}]},"B9":{"t":1,"n":"CJK UNIFIED IDEOGRAPH-84B9","V":[{"i":917760,"t":1,"c":"Adobe-Japan1","n":"CID+6414"},{"i":917761,"t":1,"c":"Hanyo-Denshi","n":"JA7269"},{"i":917761,"t":1,"c":"Moji_Joho","n":"MJ022508"},{"i":917762,"t":1,"c":"Hanyo-Denshi","n":"KS357000"},{"i":917762,"t":1,"c":"Moji_Joho","n":"MJ022510"},{"i":917763,"t":1,"c":"Hanyo-Denshi","n":"FT2485"},{"i":917763,"t":1,"c":"Moji_Joho","n":"MJ022509"}]},"BA":{"t":1,"n":"CJK UNIFIED IDEOGRAPH-84BA","V":[{"i":917760,"t":1,"c":"Adobe-Japan1","n":"CID+17088"},{"i":917761,"t":1,"c":"Hanyo-Denshi","n":"JB5685"},{"i":917761,"t":1,"c":"Moji_Joho","n":"MJ022511"},{"i":917762,"t":1,"c":"Hanyo-Denshi","n":"KS357010"},{"i":917762,"t":1,"c":"Moji_Joho","n":"MJ022512"}]},"BB":{"t":1,"n":"CJK UNIFIED IDEOGRAPH-84BB","V":[{"i":917760,"t":1,"c":"Adobe-Japan1","n":"CID+6419"},{"i":917761,"t":1,"c":"Hanyo-Denshi","n":"JA7274"},{"i":917761,"t":1,"c":"Moji_Joho","n":"MJ022513"},{"i":917762,"t":1,"c":"Hanyo-Denshi","n":"KS357020"},{"i":917762,"t":1,"c":"Moji_Joho","n":"MJ022514"},{"i":917763,"t":1,"c":"Hanyo-Denshi","n":"FT2486"},{"i":917763,"t":1,"c":"Moji_Joho","n":"MJ022515"}]},"BC":{"t":1,"n":"CJK UNIFIED IDEOGRAPH-84BC","V":[{"i":917760,"t":1,"c":"Adobe-Japan1","n":"CID+2805"},{"i":917761,"t":1,"c":"Hanyo-Denshi","n":"JA3383"},{"i":917761,"t":1,"c":"Moji_Joho","n":"MJ022516"},{"i":917762,"t":1,"c":"Hanyo-Denshi","n":"KS357060"},{"i":917762,"t":1,"c":"Moji_Joho","n":"MJ022517"}]},"BD":{"t":1,"n":"CJK UNIFIED IDEOGRAPH-84BD","V":[{"i":917760,"t":1,"c":"Adobe-Japan1","n":"CID+19746"},{"i":917761,"t":1,"c":"Hanyo-Denshi","n":"JB5686"},{"i":917761,"t":1,"c":"Moji_Joho","n":"MJ022518"},{"i":917762,"t":1,"c":"Hanyo-Denshi","n":"KS357080"},{"i":917762,"t":1,"c":"Moji_Joho","n":"MJ022519"}]},"BE":{"t":1,"n":"CJK UNIFIED IDEOGRAPH-84BE","V":[{"i":917760,"t":1,"c":"Adobe-Japan1","n":"CID+18523"},{"i":917761,"t":1,"c":"Hanyo-Denshi","n":"JB5687"},{"i":917761,"t":1,"c":"Moji_Joho","n":"MJ022520"},{"i":917762,"t":1,"c":"Hanyo-Denshi","n":"KS357100"},{"i":917762,"t":1,"c":"Moji_Joho","n":"MJ022521"}]},"BF":{"t":1,"n":"CJK UNIFIED IDEOGRAPH-84BF","V":[{"i":917760,"t":1,"c":"Adobe-Japan1","n":"CID+6415"},{"i":917761,"t":1,"c":"Hanyo-Denshi","n":"JA7270"},{"i":917761,"t":1,"c":"Moji_Joho","n":"MJ022522"},{"i":917762,"t":1,"c":"Hanyo-Denshi","n":"KS357130"},{"i":917762,"t":1,"c":"Moji_Joho","n":"MJ022523"},{"i":917763,"t":1,"c":"Hanyo-Denshi","n":"TK01080350"}]},"C0":{"t":1,"n":"CJK UNIFIED IDEOGRAPH-84C0","V":[{"i":917760,"t":1,"c":"Adobe-Japan1","n":"CID+15066"},{"i":917761,"t":1,"c":"Hanyo-Denshi","n":"JB5688"},{"i":917761,"t":1,"c":"Moji_Joho","n":"MJ022525"},{"i":917762,"t":1,"c":"Hanyo-Denshi","n":"JTBA1A"},{"i":917762,"t":1,"c":"Moji_Joho","n":"MJ022526"}]},"C1":{"t":1,"n":"CJK UNIFIED IDEOGRAPH-84C1","V":[{"i":917760,"t":1,"c":"Adobe-Japan1","n":"CID+6422"},{"i":917761,"t":1,"c":"Hanyo-Denshi","n":"JA7277"},{"i":917761,"t":1,"c":"Moji_Joho","n":"MJ022527"},{"i":917762,"t":1,"c":"Hanyo-Denshi","n":"KS357180"},{"i":917762,"t":1,"c":"Moji_Joho","n":"MJ022528"}]},"C2":{"t":1,"n":"CJK UNIFIED IDEOGRAPH-84C2","V":[{"i":917760,"t":1,"c":"Adobe-Japan1","n":"CID+15067"},{"i":917761,"t":1,"c":"Hanyo-Denshi","n":"JB5689"},{"i":917761,"t":1,"c":"Moji_Joho","n":"MJ022529"},{"i":917762,"t":1,"c":"Hanyo-Denshi","n":"JTBA1B"},{"i":917762,"t":1,"c":"Moji_Joho","n":"MJ022530"}]},"C4":{"t":1,"n":"CJK UNIFIED IDEOGRAPH-84C4","V":[{"i":917760,"t":1,"c":"Adobe-Japan1","n":"CID+2973"},{"i":917761,"t":1,"c":"Hanyo-Denshi","n":"JA3563"},{"i":917761,"t":1,"c":"Moji_Joho","n":"MJ022532"},{"i":917762,"t":1,"c":"Hanyo-Denshi","n":"KS357210"},{"i":917762,"t":1,"c":"Moji_Joho","n":"MJ022533"}]},"C5":{"t":1,"n":"CJK UNIFIED IDEOGRAPH-84C5","V":[{"i":917760,"t":1,"c":"Hanyo-Denshi","n":"IP84C5"},{"i":917760,"t":1,"c":"Moji_Joho","n":"MJ022534"},{"i":917761,"t":1,"c":"Hanyo-Denshi","n":"KS357230"},{"i":917761,"t":1,"c":"Moji_Joho","n":"MJ022535"}]},"C6":{"t":1,"n":"CJK UNIFIED IDEOGRAPH-84C6","V":[{"i":917760,"t":1,"c":"Adobe-Japan1","n":"CID+6423"},{"i":917761,"t":1,"c":"Hanyo-Denshi","n":"JA7278"},{"i":917761,"t":1,"c":"Moji_Joho","n":"MJ022536"},{"i":917762,"t":1,"c":"Hanyo-Denshi","n":"KS357240"},{"i":917762,"t":1,"c":"Moji_Joho","n":"MJ022537"}]},"C7":{"t":1,"n":"CJK UNIFIED IDEOGRAPH-84C7","V":[{"i":917760,"t":1,"c":"Adobe-Japan1","n":"CID+22352"},{"i":917761,"t":1,"c":"Hanyo-Denshi","n":"JB5690"},{"i":917761,"t":1,"c":"Moji_Joho","n":"MJ022538"},{"i":917762,"t":1,"c":"Hanyo-Denshi","n":"KS357250"},{"i":917762,"t":1,"c":"Moji_Joho","n":"MJ022539"}]},"C8":{"t":1,"n":"CJK UNIFIED IDEOGRAPH-84C8","V":[{"i":917760,"t":1,"c":"Adobe-Japan1","n":"CID+22353"},{"i":917761,"t":1,"c":"Hanyo-Denshi","n":"JB5691"},{"i":917761,"t":1,"c":"Moji_Joho","n":"MJ022540"},{"i":917762,"t":1,"c":"Hanyo-Denshi","n":"KS357260"},{"i":917762,"t":1,"c":"Moji_Joho","n":"MJ022541"},{"i":917763,"t":1,"c":"Hanyo-Denshi","n":"TK01079220"},{"i":917764,"t":1,"c":"Moji_Joho","n":"MJ060115"}]},"C9":{"t":1,"n":"CJK UNIFIED IDEOGRAPH-84C9","V":[{"i":917760,"t":1,"c":"Adobe-Japan1","n":"CID+3904"},{"i":917761,"t":1,"c":"Hanyo-Denshi","n":"JA4554"},{"i":917761,"t":1,"c":"Moji_Joho","n":"MJ022543"},{"i":917762,"t":1,"c":"Hanyo-Denshi","n":"KS357270"},{"i":917762,"t":1,"c":"Moji_Joho","n":"MJ022544"}]},"CA":{"t":1,"n":"CJK UNIFIED IDEOGRAPH-84CA","V":[{"i":917760,"t":1,"c":"Adobe-Japan1","n":"CID+6412"},{"i":917761,"t":1,"c":"Hanyo-Denshi","n":"JA7267"},{"i":917761,"t":1,"c":"Moji_Joho","n":"MJ022545"},{"i":917762,"t":1,"c":"Hanyo-Denshi","n":"KS357290S"},{"i":917762,"t":1,"c":"Moji_Joho","n":"MJ022546"},{"i":917763,"t":1,"c":"Hanyo-Denshi","n":"FT2484"},{"i":917763,"t":1,"c":"Moji_Joho","n":"MJ022548"},{"i":917764,"t":1,"c":"Hanyo-Denshi","n":"JTBA0A"},{"i":917764,"t":1,"c":"Moji_Joho","n":"MJ022547"}]},"CB":{"t":1,"n":"CJK UNIFIED IDEOGRAPH-84CB","V":[{"i":917760,"t":1,"c":"Adobe-Japan1","n":"CID+1430"},{"i":917761,"t":1,"c":"Hanyo-Denshi","n":"JA1924"},{"i":917761,"t":1,"c":"Moji_Joho","n":"MJ022549"},{"i":917762,"t":1,"c":"Hanyo-Denshi","n":"KS357310"},{"i":917762,"t":1,"c":"Moji_Joho","n":"MJ022550"}]},"CC":{"t":1,"n":"CJK UNIFIED IDEOGRAPH-84CC","V":[{"i":917760,"t":1,"c":"Adobe-Japan1","n":"CID+22354"},{"i":917761,"t":1,"c":"Hanyo-Denshi","n":"JB5692"},{"i":917761,"t":1,"c":"Moji_Joho","n":"MJ022551"},{"i":917762,"t":1,"c":"Hanyo-Denshi","n":"KS358570"},{"i":917762,"t":1,"c":"Moji_Joho","n":"MJ022552"}]},"CD":{"t":1,"n":"CJK UNIFIED IDEOGRAPH-84CD","V":[{"i":917760,"t":1,"c":"Adobe-Japan1","n":"CID+6418"},{"i":917761,"t":1,"c":"Hanyo-Denshi","n":"JA7273"},{"i":917761,"t":1,"c":"Moji_Joho","n":"MJ022553"},{"i":917762,"t":1,"c":"Hanyo-Denshi","n":"KS357330"},{"i":917762,"t":1,"c":"Moji_Joho","n":"MJ022554"}]},"CE":{"t":1,"n":"CJK UNIFIED IDEOGRAPH-84CE","V":[{"i":917760,"t":1,"c":"Adobe-Japan1","n":"CID+18525"},{"i":917761,"t":1,"c":"Hanyo-Denshi","n":"JD8658"},{"i":917761,"t":1,"c":"Moji_Joho","n":"MJ022555"},{"i":917762,"t":1,"c":"Hanyo-Denshi","n":"KS357340"},{"i":917762,"t":1,"c":"Moji_Joho","n":"MJ022556"},{"i":917763,"t":1,"c":"Hanyo-Denshi","n":"TK01080040"}]},"CF":{"t":1,"n":"CJK UNIFIED IDEOGRAPH-84CF","V":[{"i":917760,"t":1,"c":"Adobe-Japan1","n":"CID+18526"},{"i":917761,"t":1,"c":"Hanyo-Denshi","n":"JB5693"},{"i":917761,"t":1,"c":"Moji_Joho","n":"MJ022558"},{"i":917762,"t":1,"c":"Hanyo-Denshi","n":"JTBA1C"},{"i":917762,"t":1,"c":"Moji_Joho","n":"MJ022560"},{"i":917763,"t":1,"c":"Hanyo-Denshi","n":"KS357360"},{"i":917763,"t":1,"c":"Moji_Joho","n":"MJ022559"}]},"D0":{"t":1,"n":"CJK UNIFIED IDEOGRAPH-84D0","V":[{"i":917760,"t":1,"c":"Adobe-Japan1","n":"CID+6421"},{"i":917761,"t":1,"c":"Hanyo-Denshi","n":"JA7276"},{"i":917761,"t":1,"c":"Moji_Joho","n":"MJ022561"},{"i":917762,"t":1,"c":"Hanyo-Denshi","n":"KS358590"},{"i":917762,"t":1,"c":"Moji_Joho","n":"MJ022563"},{"i":917763,"t":1,"c":"Hanyo-Denshi","n":"KS357380S"},{"i":917763,"t":1,"c":"Moji_Joho","n":"MJ022562"}]},"D1":{"t":1,"n":"CJK UNIFIED IDEOGRAPH-84D1","V":[{"i":917760,"t":1,"c":"Adobe-Japan1","n":"CID+3768"},{"i":917761,"t":1,"c":"Hanyo-Denshi","n":"JA4412"},{"i":917761,"t":1,"c":"Moji_Joho","n":"MJ022564"},{"i":917762,"t":1,"c":"Hanyo-Denshi","n":"JTBA12"},{"i":917762,"t":1,"c":"Moji_Joho","n":"MJ022565"},{"i":917763,"t":1,"c":"Hanyo-Denshi","n":"TK01080000"}]},"D3":{"t":1,"n":"CJK UNIFIED IDEOGRAPH-84D3","V":[{"i":917760,"t":1,"c":"Adobe-Japan1","n":"CID+18527"},{"i":917761,"t":1,"c":"Hanyo-Denshi","n":"JB5694"},{"i":917761,"t":1,"c":"Moji_Joho","n":"MJ022568"},{"i":917762,"t":1,"c":"Hanyo-Denshi","n":"KS357410"},{"i":917762,"t":1,"c":"Moji_Joho","n":"MJ022569"}]},"D6":{"t":1,"n":"CJK UNIFIED IDEOGRAPH-84D6","V":[{"i":917760,"t":1,"c":"Adobe-Japan1","n":"CID+6424"},{"i":917761,"t":1,"c":"Hanyo-Denshi","n":"JA7279"},{"i":917761,"t":1,"c":"Moji_Joho","n":"MJ022572"},{"i":917762,"t":1,"c":"Hanyo-Denshi","n":"KS357050"},{"i":917762,"t":1,"c":"Moji_Joho","n":"MJ022573"}]},"D9":{"t":1,"n":"CJK UNIFIED IDEOGRAPH-84D9","V":[{"i":917760,"t":1,"c":"Adobe-Japan1","n":"CID+6417"},{"i":917761,"t":1,"c":"Hanyo-Denshi","n":"JA7272"},{"i":917761,"t":1,"c":"Moji_Joho","n":"MJ022576"},{"i":917762,"t":1,"c":"Hanyo-Denshi","n":"KS357780"},{"i":917762,"t":1,"c":"Moji_Joho","n":"MJ022577"},{"i":917763,"t":1,"c":"Hanyo-Denshi","n":"JTBA06"},{"i":917763,"t":1,"c":"Moji_Joho","n":"MJ022578"}]},"DA":{"t":1,"n":"CJK UNIFIED IDEOGRAPH-84DA","V":[{"i":917760,"t":1,"c":"Adobe-Japan1","n":"CID+6420"},{"i":917761,"t":1,"c":"Hanyo-Denshi","n":"JA7275"},{"i":917761,"t":1,"c":"Moji_Joho","n":"MJ022579"},{"i":917762,"t":1,"c":"Hanyo-Denshi","n":"KS357860S"},{"i":917762,"t":1,"c":"Moji_Joho","n":"MJ022580"}]},"DC":{"t":1,"n":"CJK UNIFIED IDEOGRAPH-84DC","V":[{"i":917760,"t":1,"c":"Adobe-Japan1","n":"CID+8363"},{"i":917761,"t":1,"c":"Hanyo-Denshi","n":"JB5701"},{"i":917761,"t":1,"c":"Moji_Joho","n":"MJ022582"},{"i":917762,"t":1,"c":"Hanyo-Denshi","n":"JTBA19"},{"i":917762,"t":1,"c":"Moji_Joho","n":"MJ022581"},{"i":917763,"t":1,"c":"Hanyo-Denshi","n":"JTB9E8"},{"i":917763,"t":1,"c":"Moji_Joho","n":"MJ022583"},{"i":917764,"t":1,"c":"Hanyo-Denshi","n":"TK01079440"}]},"DD":{"t":1,"n":"CJK UNIFIED IDEOGRAPH-84DD","V":[{"i":917760,"t":1,"c":"Hanyo-Denshi","n":"TK01079500"},{"i":917761,"t":1,"c":"Hanyo-Denshi","n":"TK01079720"}]},"E7":{"t":1,"n":"CJK UNIFIED IDEOGRAPH-84E7","V":[{"i":917760,"t":1,"c":"Adobe-Japan1","n":"CID+18529"},{"i":917761,"t":1,"c":"Hanyo-Denshi","n":"JB5702"},{"i":917761,"t":1,"c":"Moji_Joho","n":"MJ022590"},{"i":917762,"t":1,"c":"Hanyo-Denshi","n":"JTBA33"},{"i":917762,"t":1,"c":"Moji_Joho","n":"MJ022589"}]},"EA":{"t":1,"n":"CJK UNIFIED IDEOGRAPH-84EA","V":[{"i":917760,"t":1,"c":"Adobe-Japan1","n":"CID+18530"},{"i":917761,"t":1,"c":"Adobe-Japan1","n":"CID+20205"},{"i":917762,"t":1,"c":"Hanyo-Denshi","n":"JB5703"},{"i":917762,"t":1,"c":"Moji_Joho","n":"MJ022593"},{"i":917763,"t":1,"c":"Hanyo-Denshi","n":"KS358660"},{"i":917763,"t":1,"c":"Moji_Joho","n":"MJ022594"}]},"EB":{"t":1,"n":"CJK UNIFIED IDEOGRAPH-84EB","V":[{"i":917760,"t":1,"c":"Hanyo-Denshi","n":"IB0361"},{"i":917760,"t":1,"c":"Moji_Joho","n":"MJ022596"},{"i":917761,"t":1,"c":"Hanyo-Denshi","n":"IB0868"},{"i":917761,"t":1,"c":"Moji_Joho","n":"MJ022595"}]},"EC":{"t":1,"n":"CJK UNIFIED IDEOGRAPH-84EC","V":[{"i":917760,"t":1,"c":"Adobe-Japan1","n":"CID+3671"},{"i":917761,"t":1,"c":"Adobe-Japan1","n":"CID+7794"},{"i":917762,"t":1,"c":"Hanyo-Denshi","n":"JA4309"},{"i":917762,"t":1,"c":"Moji_Joho","n":"MJ022597"},{"i":917763,"t":1,"c":"Hanyo-Denshi","n":"FT1921"},{"i":917763,"t":1,"c":"Moji_Joho","n":"MJ022599"},{"i":917764,"t":1,"c":"Hanyo-Denshi","n":"KS358710"},{"i":917764,"t":1,"c":"Moji_Joho","n":"MJ022600"},{"i":917765,"t":1,"c":"Hanyo-Denshi","n":"JTBCF0"},{"i":917765,"t":1,"c":"Moji_Joho","n":"MJ022598"},{"i":917766,"t":1,"c":"Hanyo-Denshi","n":"JTBD11"},{"i":917766,"t":1,"c":"Moji_Joho","n":"MJ022601"}]},"EE":{"t":1,"n":"CJK UNIFIED IDEOGRAPH-84EE","V":[{"i":65024,"t":2,"c":3,"n":"CJK COMPATIBILITY IDEOGRAPH-F999"},{"i":917760,"t":1,"c":"Adobe-Japan1","n":"CID+7811"},{"i":917761,"t":1,"c":"Adobe-Japan1","n":"CID+4039"},{"i":917762,"t":1,"c":"Hanyo-Denshi","n":"JA4701"},{"i":917762,"t":1,"c":"Moji_Joho","n":"MJ022603"},{"i":917763,"t":1,"c":"Hanyo-Denshi","n":"KS358730"},{"i":917763,"t":1,"c":"Moji_Joho","n":"MJ022606"},{"i":917764,"t":1,"c":"Hanyo-Denshi","n":"FT1939"},{"i":917764,"t":1,"c":"Moji_Joho","n":"MJ022605"},{"i":917765,"t":1,"c":"Hanyo-Denshi","n":"JTBCFD"},{"i":917765,"t":1,"c":"Moji_Joho","n":"MJ022604"},{"i":917766,"t":1,"c":"Hanyo-Denshi","n":"JTBD10"},{"i":917766,"t":1,"c":"Moji_Joho","n":"MJ022607"},{"i":917767,"t":1,"c":"Hanyo-Denshi","n":"TK01079970"}]},"EF":{"t":1,"n":"CJK UNIFIED IDEOGRAPH-84EF","V":[{"i":917760,"t":1,"c":"Adobe-Japan1","n":"CID+18531"},{"i":917761,"t":1,"c":"Hanyo-Denshi","n":"JB5704"},{"i":917761,"t":1,"c":"Moji_Joho","n":"MJ022609"},{"i":917762,"t":1,"c":"Hanyo-Denshi","n":"KS358750"},{"i":917762,"t":1,"c":"Moji_Joho","n":"MJ022610"}]},"F0":{"t":1,"n":"CJK UNIFIED IDEOGRAPH-84F0","V":[{"i":917760,"t":1,"c":"Adobe-Japan1","n":"CID+15068"},{"i":917761,"t":1,"c":"Hanyo-Denshi","n":"JB5705"},{"i":917761,"t":1,"c":"Moji_Joho","n":"MJ022612"},{"i":917762,"t":1,"c":"Hanyo-Denshi","n":"JTBA32"},{"i":917762,"t":1,"c":"Moji_Joho","n":"MJ022611"}]},"F1":{"t":1,"n":"CJK UNIFIED IDEOGRAPH-84F1","V":[{"i":65024,"t":2,"c":3,"n":"CJK COMPATIBILITY IDEOGRAPH-2F9A8"},{"i":917760,"t":1,"c":"Adobe-Japan1","n":"CID+18532"},{"i":917761,"t":1,"c":"Hanyo-Denshi","n":"JB5706"},{"i":917761,"t":1,"c":"Moji_Joho","n":"MJ022614"},{"i":917762,"t":1,"c":"Hanyo-Denshi","n":"KS358780"},{"i":917762,"t":1,"c":"Moji_Joho","n":"MJ022615"},{"i":917763,"t":1,"c":"Hanyo-Denshi","n":"KS356000"},{"i":917763,"t":1,"c":"Moji_Joho","n":"MJ022613"}]},"F2":{"t":1,"n":"CJK UNIFIED IDEOGRAPH-84F2","V":[{"i":917760,"t":1,"c":"Adobe-Japan1","n":"CID+22355"},{"i":917761,"t":1,"c":"Hanyo-Denshi","n":"JB5707"},{"i":917761,"t":1,"c":"Moji_Joho","n":"MJ022616"},{"i":917762,"t":1,"c":"Hanyo-Denshi","n":"KS358810"},{"i":917762,"t":1,"c":"Moji_Joho","n":"MJ022617"}]},"F3":{"t":1,"n":"CJK UNIFIED IDEOGRAPH-84F3","V":[{"i":65024,"t":2,"c":3,"n":"CJK COMPATIBILITY IDEOGRAPH-2F9A9"}]},"F4":{"t":1,"n":"CJK UNIFIED IDEOGRAPH-84F4","V":[{"i":917760,"t":1,"c":"Adobe-Japan1","n":"CID+6428"},{"i":917761,"t":1,"c":"Adobe-Japan1","n":"CID+14205"},{"i":917762,"t":1,"c":"Hanyo-Denshi","n":"JA7283"},{"i":917762,"t":1,"c":"Moji_Joho","n":"MJ022619"},{"i":917763,"t":1,"c":"Hanyo-Denshi","n":"KS358850"},{"i":917763,"t":1,"c":"Moji_Joho","n":"MJ022620"},{"i":917764,"t":1,"c":"Hanyo-Denshi","n":"JTBA28"},{"i":917764,"t":1,"c":"Moji_Joho","n":"MJ022621"}]},"F7":{"t":1,"n":"CJK UNIFIED IDEOGRAPH-84F7","V":[{"i":917760,"t":1,"c":"Adobe-Japan1","n":"CID+22356"},{"i":917761,"t":1,"c":"Hanyo-Denshi","n":"JB5708"},{"i":917761,"t":1,"c":"Moji_Joho","n":"MJ022624"},{"i":917762,"t":1,"c":"Hanyo-Denshi","n":"JTBA34"},{"i":917762,"t":1,"c":"Moji_Joho","n":"MJ022625"}]},"FA":{"t":1,"n":"CJK UNIFIED IDEOGRAPH-84FA","V":[{"i":917760,"t":1,"c":"Adobe-Japan1","n":"CID+18533"}]},"FB":{"t":1,"n":"CJK UNIFIED IDEOGRAPH-84FB","V":[{"i":917760,"t":1,"c":"Adobe-Japan1","n":"CID+19747"},{"i":917761,"t":1,"c":"Hanyo-Denshi","n":"JB5711"},{"i":917761,"t":1,"c":"Moji_Joho","n":"MJ022629"},{"i":917762,"t":1,"c":"Hanyo-Denshi","n":"KS358930"},{"i":917762,"t":1,"c":"Moji_Joho","n":"MJ022630"}]},"FC":{"t":1,"n":"CJK UNIFIED IDEOGRAPH-84FC","V":[{"i":65024,"t":2,"c":3,"n":"CJK COMPATIBILITY IDEOGRAPH-F9C2"},{"i":917760,"t":1,"c":"Adobe-Japan1","n":"CID+6435"},{"i":917761,"t":1,"c":"Hanyo-Denshi","n":"JA7290"},{"i":917761,"t":1,"c":"Moji_Joho","n":"MJ022631"},{"i":917762,"t":1,"c":"Hanyo-Denshi","n":"KS358940"},{"i":917762,"t":1,"c":"Moji_Joho","n":"MJ022632"},{"i":917763,"t":1,"c":"Hanyo-Denshi","n":"FT2488"},{"i":917763,"t":1,"c":"Moji_Joho","n":"MJ022633"}]},"FD":{"t":1,"n":"CJK UNIFIED IDEOGRAPH-84FD","V":[{"i":917760,"t":1,"c":"Adobe-Japan1","n":"CID+15069"},{"i":917761,"t":1,"c":"Hanyo-Denshi","n":"JB5712"},{"i":917761,"t":1,"c":"Moji_Joho","n":"MJ022634"},{"i":917762,"t":1,"c":"Hanyo-Denshi","n":"KS361110"},{"i":917762,"t":1,"c":"Moji_Joho","n":"MJ022636"},{"i":917763,"t":1,"c":"Hanyo-Denshi","n":"KS358950"},{"i":917763,"t":1,"c":"Moji_Joho","n":"MJ022635"}]},"FF":{"t":1,"n":"CJK UNIFIED IDEOGRAPH-84FF","V":[{"i":917760,"t":1,"c":"Adobe-Japan1","n":"CID+6427"},{"i":917761,"t":1,"c":"Hanyo-Denshi","n":"JA7282"},{"i":917761,"t":1,"c":"Moji_Joho","n":"MJ022638"},{"i":917762,"t":1,"c":"Hanyo-Denshi","n":"KS358970"},{"i":917762,"t":1,"c":"Moji_Joho","n":"MJ022639"}]}}