{"1C":{"t":1,"n":"CJK UNIFIED IDEOGRAPH-961C","V":[{"i":917760,"t":1,"c":"Adobe-Japan1","n":"CID+3550"}]},"1D":{"t":1,"n":"CJK UNIFIED IDEOGRAPH-961D","V":[{"i":917760,"t":1,"c":"Adobe-Japan1","n":"CID+15262"}]},"1E":{"t":1,"n":"CJK UNIFIED IDEOGRAPH-961E","V":[{"i":917760,"t":1,"c":"Adobe-Japan1","n":"CID+22826"}]},"21":{"t":1,"n":"CJK UNIFIED IDEOGRAPH-9621","V":[{"i":917760,"t":1,"c":"Adobe-Japan1","n":"CID+7087"}]},"22":{"t":1,"n":"CJK UNIFIED IDEOGRAPH-9622","V":[{"i":917760,"t":1,"c":"Adobe-Japan1","n":"CID+22827"}]},"24":{"t":1,"n":"CJK UNIFIED IDEOGRAPH-9624","V":[{"i":917760,"t":1,"c":"Adobe-Japan1","n":"CID+19952"}]},"25":{"t":1,"n":"CJK UNIFIED IDEOGRAPH-9625","V":[{"i":917760,"t":1,"c":"Adobe-Japan1","n":"CID+22828"}]},"26":{"t":1,"n":"CJK UNIFIED IDEOGRAPH-9626","V":[{"i":917760,"t":1,"c":"Adobe-Japan1","n":"CID+22829"}]},"28":{"t":1,"n":"CJK UNIFIED IDEOGRAPH-9628","V":[{"i":917760,"t":1,"c":"Adobe-Japan1","n":"CID+7088"}]},"2A":{"t":1,"n":"CJK UNIFIED IDEOGRAPH-962A","V":[{"i":917760,"t":1,"c":"Adobe-Japan1","n":"CID+2133"},{"i":917761,"t":1,"c":"Adobe-Japan1","n":"CID+20242"}]},"2C":{"t":1,"n":"CJK UNIFIED IDEOGRAPH-962C","V":[{"i":917760,"t":1,"c":"Adobe-Japan1","n":"CID+18887"}]},"2E":{"t":1,"n":"CJK UNIFIED IDEOGRAPH-962E","V":[{"i":65024,"t":2,"c":3,"n":"CJK COMPATIBILITY IDEOGRAPH-F9C6"},{"i":917760,"t":1,"c":"Adobe-Japan1","n":"CID+7089"}]},"2F":{"t":1,"n":"CJK UNIFIED IDEOGRAPH-962F","V":[{"i":917760,"t":1,"c":"Adobe-Japan1","n":"CID+7090"}]},"31":{"t":1,"n":"CJK UNIFIED IDEOGRAPH-9631","V":[{"i":917760,"t":1,"c":"Adobe-Japan1","n":"CID+19953"}]},"32":{"t":1,"n":"CJK UNIFIED IDEOGRAPH-9632","V":[{"i":917760,"t":1,"c":"Adobe-Japan1","n":"CID+3703"}]},"33":{"t":1,"n":"CJK UNIFIED IDEOGRAPH-9633","V":[{"i":917760,"t":1,"c":"Adobe-Japan1","n":"CID+18888"}]},"34":{"t":1,"n":"CJK UNIFIED IDEOGRAPH-9634","V":[{"i":917760,"t":1,"c":"Adobe-Japan1","n":"CID+18889"}]},"37":{"t":1,"n":"CJK UNIFIED IDEOGRAPH-9637","V":[{"i":917760,"t":1,"c":"Adobe-Japan1","n":"CID+22830"}]},"38":{"t":1,"n":"CJK UNIFIED IDEOGRAPH-9638","V":[{"i":917760,"t":1,"c":"Adobe-Japan1","n":"CID+19954"}]},"39":{"t":1,"n":"CJK UNIFIED IDEOGRAPH-9639","V":[{"i":917760,"t":1,"c":"Adobe-Japan1","n":"CID+22831"}]},"3A":{"t":1,"n":"CJK UNIFIED IDEOGRAPH-963A","V":[{"i":917760,"t":1,"c":"Adobe-Japan1","n":"CID+22832"}]},"3B":{"t":1,"n":"CJK UNIFIED IDEOGRAPH-963B","V":[{"i":917760,"t":1,"c":"Adobe-Japan1","n":"CID+2765"}]},"3C":{"t":1,"n":"CJK UNIFIED IDEOGRAPH-963C","V":[{"i":917760,"t":1,"c":"Adobe-Japan1","n":"CID+18891"}]},"3D":{"t":1,"n":"CJK UNIFIED IDEOGRAPH-963D","V":[{"i":917760,"t":1,"c":"Adobe-Japan1","n":"CID+19955"}]},"3F":{"t":1,"n":"CJK UNIFIED IDEOGRAPH-963F","V":[{"i":917760,"t":1,"c":"Adobe-Japan1","n":"CID+1128"}]},"40":{"t":1,"n":"CJK UNIFIED IDEOGRAPH-9640","V":[{"i":917760,"t":1,"c":"Adobe-Japan1","n":"CID+2859"}]},"41":{"t":1,"n":"CJK UNIFIED IDEOGRAPH-9641","V":[{"i":917760,"t":1,"c":"Adobe-Japan1","n":"CID+15263"}]},"42":{"t":1,"n":"CJK UNIFIED IDEOGRAPH-9642","V":[{"i":917760,"t":1,"c":"Adobe-Japan1","n":"CID+7091"}]},"44":{"t":1,"n":"CJK UNIFIED IDEOGRAPH-9644","V":[{"i":917760,"t":1,"c":"Adobe-Japan1","n":"CID+3551"}]},"46":{"t":1,"n":"CJK UNIFIED IDEOGRAPH-9646","V":[{"i":917760,"t":1,"c":"Hanyo-Denshi","n":"TK01095450"},{"i":917761,"t":1,"c":"Hanyo-Denshi","n":"TK01095530"}]},"4B":{"t":1,"n":"CJK UNIFIED IDEOGRAPH-964B","V":[{"i":65024,"t":2,"c":3,"n":"CJK COMPATIBILITY IDEOGRAPH-F951"},{"i":917760,"t":1,"c":"Adobe-Japan1","n":"CID+7094"}]},"4C":{"t":1,"n":"CJK UNIFIED IDEOGRAPH-964C","V":[{"i":917760,"t":1,"c":"Adobe-Japan1","n":"CID+7092"}]},"4D":{"t":1,"n":"CJK UNIFIED IDEOGRAPH-964D","V":[{"i":65024,"t":2,"c":3,"n":"CJK COMPATIBILITY IDEOGRAPH-FA09"},{"i":917760,"t":1,"c":"Adobe-Japan1","n":"CID+2033"},{"i":917761,"t":1,"c":"Adobe-Japan1","n":"CID+13447"},{"i":917762,"t":1,"c":"Hanyo-Denshi","n":"JA2563"},{"i":917762,"t":1,"c":"Moji_Joho","n":"MJ027575"},{"i":917763,"t":1,"c":"Hanyo-Denshi","n":"KS472040"},{"i":917763,"t":1,"c":"Moji_Joho","n":"MJ027574"},{"i":917764,"t":1,"c":"Moji_Joho","n":"MJ027576"}]},"4F":{"t":1,"n":"CJK UNIFIED IDEOGRAPH-964F","V":[{"i":917760,"t":1,"c":"Adobe-Japan1","n":"CID+7093"}]},"50":{"t":1,"n":"CJK UNIFIED IDEOGRAPH-9650","V":[{"i":917760,"t":1,"c":"Adobe-Japan1","n":"CID+1910"}]},"52":{"t":1,"n":"CJK UNIFIED IDEOGRAPH-9652","V":[{"i":917760,"t":1,"c":"Adobe-Japan1","n":"CID+22833"}]},"54":{"t":1,"n":"CJK UNIFIED IDEOGRAPH-9654","V":[{"i":917760,"t":1,"c":"Adobe-Japan1","n":"CID+19956"},{"i":917761,"t":1,"c":"Hanyo-Denshi","n":"JB7053"},{"i":917761,"t":1,"c":"Moji_Joho","n":"MJ027583"},{"i":917762,"t":1,"c":"Hanyo-Denshi","n":"JTBE6E"},{"i":917762,"t":1,"c":"Moji_Joho","n":"MJ027584"}]},"56":{"t":1,"n":"CJK UNIFIED IDEOGRAPH-9656","V":[{"i":917760,"t":1,"c":"Adobe-Japan1","n":"CID+22834"}]},"57":{"t":1,"n":"CJK UNIFIED IDEOGRAPH-9657","V":[{"i":917760,"t":1,"c":"Adobe-Japan1","n":"CID+22835"},{"i":917761,"t":1,"c":"Hanyo-Denshi","n":"JB7055"},{"i":917762,"t":1,"c":"Hanyo-Denshi","n":"TK01095650"}]},"58":{"t":1,"n":"CJK UNIFIED IDEOGRAPH-9658","V":[{"i":917760,"t":1,"c":"Adobe-Japan1","n":"CID+15264"}]},"5B":{"t":1,"n":"CJK UNIFIED IDEOGRAPH-965B","V":[{"i":917760,"t":1,"c":"Adobe-Japan1","n":"CID+3605"}]},"5C":{"t":1,"n":"CJK UNIFIED IDEOGRAPH-965C","V":[{"i":917760,"t":1,"c":"Adobe-Japan1","n":"CID+7096"}]},"5D":{"t":1,"n":"CJK UNIFIED IDEOGRAPH-965D","V":[{"i":917760,"t":1,"c":"Adobe-Japan1","n":"CID+7098"}]},"5E":{"t":1,"n":"CJK UNIFIED IDEOGRAPH-965E","V":[{"i":917760,"t":1,"c":"Adobe-Japan1","n":"CID+7097"}]},"5F":{"t":1,"n":"CJK UNIFIED IDEOGRAPH-965F","V":[{"i":917760,"t":1,"c":"Adobe-Japan1","n":"CID+7099"},{"i":917761,"t":1,"c":"Hanyo-Denshi","n":"JA8002"},{"i":917761,"t":1,"c":"Moji_Joho","n":"MJ027596"},{"i":917762,"t":1,"c":"Hanyo-Denshi","n":"FT2662"},{"i":917762,"t":1,"c":"Moji_Joho","n":"MJ027597"}]},"61":{"t":1,"n":"CJK UNIFIED IDEOGRAPH-9661","V":[{"i":917760,"t":1,"c":"Adobe-Japan1","n":"CID+18892"}]},"62":{"t":1,"n":"CJK UNIFIED IDEOGRAPH-9662","V":[{"i":917760,"t":1,"c":"Adobe-Japan1","n":"CID+1219"}]},"63":{"t":1,"n":"CJK UNIFIED IDEOGRAPH-9663","V":[{"i":917760,"t":1,"c":"Adobe-Japan1","n":"CID+2590"}]},"64":{"t":1,"n":"CJK UNIFIED IDEOGRAPH-9664","V":[{"i":917760,"t":1,"c":"Adobe-Japan1","n":"CID+2438"}]},"65":{"t":1,"n":"CJK UNIFIED IDEOGRAPH-9665","V":[{"i":917760,"t":1,"c":"Adobe-Japan1","n":"CID+1557"}]},"66":{"t":1,"n":"CJK UNIFIED IDEOGRAPH-9666","V":[{"i":917760,"t":1,"c":"Adobe-Japan1","n":"CID+7100"}]},"6A":{"t":1,"n":"CJK UNIFIED IDEOGRAPH-966A","V":[{"i":917760,"t":1,"c":"Adobe-Japan1","n":"CID+3356"}]},"6C":{"t":1,"n":"CJK UNIFIED IDEOGRAPH-966C","V":[{"i":917760,"t":1,"c":"Adobe-Japan1","n":"CID+7102"}]},"6E":{"t":1,"n":"CJK UNIFIED IDEOGRAPH-966E","V":[{"i":917760,"t":1,"c":"Adobe-Japan1","n":"CID+22836"}]},"70":{"t":1,"n":"CJK UNIFIED IDEOGRAPH-9670","V":[{"i":917760,"t":1,"c":"Adobe-Japan1","n":"CID+1220"}]},"72":{"t":1,"n":"CJK UNIFIED IDEOGRAPH-9672","V":[{"i":917760,"t":1,"c":"Adobe-Japan1","n":"CID+7101"}]},"73":{"t":1,"n":"CJK UNIFIED IDEOGRAPH-9673","V":[{"i":917760,"t":1,"c":"Adobe-Japan1","n":"CID+3040"}]},"74":{"t":1,"n":"CJK UNIFIED IDEOGRAPH-9674","V":[{"i":917760,"t":1,"c":"Adobe-Japan1","n":"CID+19957"}]},"75":{"t":1,"n":"CJK UNIFIED IDEOGRAPH-9675","V":[{"i":65024,"t":2,"c":3,"n":"CJK COMPATIBILITY IDEOGRAPH-F959"},{"i":917760,"t":1,"c":"Adobe-Japan1","n":"CID+3989"},{"i":917761,"t":1,"c":"Hanyo-Denshi","n":"JA4645"},{"i":917761,"t":1,"c":"Moji_Joho","n":"MJ027617"},{"i":917762,"t":1,"c":"Hanyo-Denshi","n":"KS472960"},{"i":917762,"t":1,"c":"Moji_Joho","n":"MJ027616"}]},"76":{"t":1,"n":"CJK UNIFIED IDEOGRAPH-9676","V":[{"i":917760,"t":1,"c":"Adobe-Japan1","n":"CID+3203"},{"i":917761,"t":1,"c":"Hanyo-Denshi","n":"JA3811"},{"i":917762,"t":1,"c":"Hanyo-Denshi","n":"TK01095960"}]},"77":{"t":1,"n":"CJK UNIFIED IDEOGRAPH-9677","V":[{"i":917760,"t":1,"c":"Adobe-Japan1","n":"CID+7095"},{"i":917761,"t":1,"c":"Hanyo-Denshi","n":"JA7992"},{"i":917762,"t":1,"c":"Hanyo-Denshi","n":"TK01095520"}]},"78":{"t":1,"n":"CJK UNIFIED IDEOGRAPH-9678","V":[{"i":65024,"t":2,"c":3,"n":"CJK COMPATIBILITY IDEOGRAPH-F9D3"},{"i":917760,"t":1,"c":"Adobe-Japan1","n":"CID+3950"}]},"7A":{"t":1,"n":"CJK UNIFIED IDEOGRAPH-967A","V":[{"i":917760,"t":1,"c":"Adobe-Japan1","n":"CID+1893"}]},"7B":{"t":1,"n":"CJK UNIFIED IDEOGRAPH-967B","V":[{"i":917760,"t":1,"c":"Adobe-Japan1","n":"CID+19958"},{"i":917761,"t":1,"c":"Hanyo-Denshi","n":"JB7060"},{"i":917761,"t":1,"c":"Moji_Joho","n":"MJ027623"},{"i":917762,"t":1,"c":"Hanyo-Denshi","n":"KS473640"},{"i":917762,"t":1,"c":"Moji_Joho","n":"MJ027624"}]},"7C":{"t":1,"n":"CJK UNIFIED IDEOGRAPH-967C","V":[{"i":65024,"t":2,"c":3,"n":"CJK COMPATIBILITY IDEOGRAPH-FAC6"},{"i":917760,"t":1,"c":"Adobe-Japan1","n":"CID+22837"}]},"7D":{"t":1,"n":"CJK UNIFIED IDEOGRAPH-967D","V":[{"i":917760,"t":1,"c":"Adobe-Japan1","n":"CID+3909"}]},"7E":{"t":1,"n":"CJK UNIFIED IDEOGRAPH-967E","V":[{"i":917760,"t":1,"c":"Adobe-Japan1","n":"CID+22838"}]},"7F":{"t":1,"n":"CJK UNIFIED IDEOGRAPH-967F","V":[{"i":917760,"t":1,"c":"Adobe-Japan1","n":"CID+19959"},{"i":917761,"t":1,"c":"Moji_Joho","n":"MJ027628"},{"i":917762,"t":1,"c":"Moji_Joho","n":"MJ027629"}]},"81":{"t":1,"n":"CJK UNIFIED IDEOGRAPH-9681","V":[{"i":917760,"t":1,"c":"Adobe-Japan1","n":"CID+19960"},{"i":917761,"t":1,"c":"Moji_Joho","n":"MJ027631"},{"i":917762,"t":1,"c":"Moji_Joho","n":"MJ027632"}]},"82":{"t":1,"n":"CJK UNIFIED IDEOGRAPH-9682","V":[{"i":917760,"t":1,"c":"Adobe-Japan1","n":"CID+18894"},{"i":917761,"t":1,"c":"Hanyo-Denshi","n":"JB7065"},{"i":917761,"t":1,"c":"Moji_Joho","n":"MJ027633"},{"i":917762,"t":1,"c":"Hanyo-Denshi","n":"JTBE7C"},{"i":917762,"t":1,"c":"Moji_Joho","n":"MJ027634"}]},"83":{"t":1,"n":"CJK UNIFIED IDEOGRAPH-9683","V":[{"i":917760,"t":1,"c":"Adobe-Japan1","n":"CID+19961"},{"i":917761,"t":1,"c":"Hanyo-Denshi","n":"JB7066"},{"i":917762,"t":1,"c":"Hanyo-Denshi","n":"TK01095860"}]},"84":{"t":1,"n":"CJK UNIFIED IDEOGRAPH-9684","V":[{"i":917760,"t":1,"c":"Adobe-Japan1","n":"CID+15265"}]},"85":{"t":1,"n":"CJK UNIFIED IDEOGRAPH-9685","V":[{"i":917760,"t":1,"c":"Adobe-Japan1","n":"CID+1777"}]},"86":{"t":1,"n":"CJK UNIFIED IDEOGRAPH-9686","V":[{"i":65024,"t":2,"c":3,"n":"CJK COMPATIBILITY IDEOGRAPH-F9DC"},{"i":917760,"t":1,"c":"Adobe-Japan1","n":"CID+3964"},{"i":917761,"t":1,"c":"Adobe-Japan1","n":"CID+13393"},{"i":917762,"t":1,"c":"Adobe-Japan1","n":"CID+8686"},{"i":917763,"t":1,"c":"Hanyo-Denshi","n":"JA4620"},{"i":917763,"t":1,"c":"Moji_Joho","n":"MJ027639"},{"i":917764,"t":1,"c":"Hanyo-Denshi","n":"IB1029"},{"i":917764,"t":1,"c":"Moji_Joho","n":"MJ027640"},{"i":917765,"t":1,"c":"Hanyo-Denshi","n":"JTBE75"},{"i":917765,"t":1,"c":"Moji_Joho","n":"MJ030190"},{"i":917766,"t":1,"c":"Hanyo-Denshi","n":"JC9361"},{"i":917766,"t":1,"c":"Moji_Joho","n":"MJ030189"}]},"88":{"t":1,"n":"CJK UNIFIED IDEOGRAPH-9688","V":[{"i":917760,"t":1,"c":"Adobe-Japan1","n":"CID+1790"}]},"89":{"t":1,"n":"CJK UNIFIED IDEOGRAPH-9689","V":[{"i":917760,"t":1,"c":"Adobe-Japan1","n":"CID+19962"}]},"8A":{"t":1,"n":"CJK UNIFIED IDEOGRAPH-968A","V":[{"i":917760,"t":1,"c":"Adobe-Japan1","n":"CID+2882"},{"i":917761,"t":1,"c":"Adobe-Japan1","n":"CID+13907"},{"i":917762,"t":1,"c":"Hanyo-Denshi","n":"JA3466"},{"i":917762,"t":1,"c":"Moji_Joho","n":"MJ027645"},{"i":917763,"t":1,"c":"Hanyo-Denshi","n":"FT2041"},{"i":917763,"t":1,"c":"Moji_Joho","n":"MJ027646"},{"i":917764,"t":1,"c":"Hanyo-Denshi","n":"JTBE79S"},{"i":917764,"t":1,"c":"Moji_Joho","n":"MJ027644"}]},"8B":{"t":1,"n":"CJK UNIFIED IDEOGRAPH-968B","V":[{"i":917760,"t":1,"c":"Adobe-Japan1","n":"CID+6252"}]},"8D":{"t":1,"n":"CJK UNIFIED IDEOGRAPH-968D","V":[{"i":917760,"t":1,"c":"Adobe-Japan1","n":"CID+7103"}]},"8E":{"t":1,"n":"CJK UNIFIED IDEOGRAPH-968E","V":[{"i":917760,"t":1,"c":"Adobe-Japan1","n":"CID+1418"}]},"8F":{"t":1,"n":"CJK UNIFIED IDEOGRAPH-968F","V":[{"i":917760,"t":1,"c":"Adobe-Japan1","n":"CID+2613"}]},"91":{"t":1,"n":"CJK UNIFIED IDEOGRAPH-9691","V":[{"i":917760,"t":1,"c":"Adobe-Japan1","n":"CID+22839"}]},"92":{"t":1,"n":"CJK UNIFIED IDEOGRAPH-9692","V":[{"i":917760,"t":1,"c":"Hanyo-Denshi","n":"IP9692"},{"i":917761,"t":1,"c":"Hanyo-Denshi","n":"TK01096030"}]},"94":{"t":1,"n":"CJK UNIFIED IDEOGRAPH-9694","V":[{"i":917760,"t":1,"c":"Adobe-Japan1","n":"CID+1460"},{"i":917761,"t":1,"c":"Adobe-Japan1","n":"CID+13683"},{"i":917762,"t":1,"c":"Hanyo-Denshi","n":"JA1954"},{"i":917762,"t":1,"c":"Moji_Joho","n":"MJ027657"},{"i":917763,"t":1,"c":"Hanyo-Denshi","n":"JTBE7B"},{"i":917763,"t":1,"c":"Moji_Joho","n":"MJ027656"}]},"95":{"t":1,"n":"CJK UNIFIED IDEOGRAPH-9695","V":[{"i":917760,"t":1,"c":"Adobe-Japan1","n":"CID+7105"}]},"96":{"t":1,"n":"CJK UNIFIED IDEOGRAPH-9696","V":[{"i":917760,"t":1,"c":"Adobe-Japan1","n":"CID+19963"}]},"97":{"t":1,"n":"CJK UNIFIED IDEOGRAPH-9697","V":[{"i":917760,"t":1,"c":"Adobe-Japan1","n":"CID+7106"}]},"98":{"t":1,"n":"CJK UNIFIED IDEOGRAPH-9698","V":[{"i":917760,"t":1,"c":"Adobe-Japan1","n":"CID+7104"},{"i":917761,"t":1,"c":"Adobe-Japan1","n":"CID+13621"},{"i":917762,"t":1,"c":"Adobe-Japan1","n":"CID+20243"},{"i":917763,"t":1,"c":"Hanyo-Denshi","n":"JA8007"},{"i":917763,"t":1,"c":"Moji_Joho","n":"MJ027661"},{"i":917764,"t":1,"c":"Hanyo-Denshi","n":"FT2663S"},{"i":917764,"t":1,"c":"Moji_Joho","n":"MJ027662"},{"i":917765,"t":1,"c":"Hanyo-Denshi","n":"JTBE7F"},{"i":917765,"t":1,"c":"Moji_Joho","n":"MJ027664"},{"i":917766,"t":1,"c":"Hanyo-Denshi","n":"JTBE7E"},{"i":917766,"t":1,"c":"Moji_Joho","n":"MJ027663"}]},"99":{"t":1,"n":"CJK UNIFIED IDEOGRAPH-9699","V":[{"i":917760,"t":1,"c":"Adobe-Japan1","n":"CID+1850"},{"i":917761,"t":1,"c":"Adobe-Japan1","n":"CID+20273"},{"i":917762,"t":1,"c":"Moji_Joho","n":"MJ027665"},{"i":917763,"t":1,"c":"Moji_Joho","n":"MJ027666"}]},"9A":{"t":1,"n":"CJK UNIFIED IDEOGRAPH-969A","V":[{"i":917760,"t":1,"c":"Adobe-Japan1","n":"CID+18896"}]},"9B":{"t":1,"n":"CJK UNIFIED IDEOGRAPH-969B","V":[{"i":917760,"t":1,"c":"Adobe-Japan1","n":"CID+2125"}]},"9C":{"t":1,"n":"CJK UNIFIED IDEOGRAPH-969C","V":[{"i":917760,"t":1,"c":"Adobe-Japan1","n":"CID+2507"},{"i":917761,"t":1,"c":"Hanyo-Denshi","n":"JA3067"},{"i":917761,"t":1,"c":"Moji_Joho","n":"MJ027669"},{"i":917762,"t":1,"c":"Hanyo-Denshi","n":"JTBE81"},{"i":917762,"t":1,"c":"Moji_Joho","n":"MJ027670"}]},"9D":{"t":1,"n":"CJK UNIFIED IDEOGRAPH-969D","V":[{"i":917760,"t":1,"c":"Adobe-Japan1","n":"CID+8688"}]},"9F":{"t":1,"n":"CJK UNIFIED IDEOGRAPH-969F","V":[{"i":917760,"t":1,"c":"Adobe-Japan1","n":"CID+22840"}]},"A0":{"t":1,"n":"CJK UNIFIED IDEOGRAPH-96A0","V":[{"i":917760,"t":1,"c":"Adobe-Japan1","n":"CID+1221"},{"i":917761,"t":1,"c":"Hanyo-Denshi","n":"JA1703"},{"i":917761,"t":1,"c":"Moji_Joho","n":"MJ027675"},{"i":917762,"t":1,"c":"Hanyo-Denshi","n":"KS474430"},{"i":917762,"t":1,"c":"Moji_Joho","n":"MJ027674"}]},"A3":{"t":1,"n":"CJK UNIFIED IDEOGRAPH-96A3","V":[{"i":65024,"t":2,"c":3,"n":"CJK COMPATIBILITY IDEOGRAPH-F9F1"},{"i":917760,"t":1,"c":"Adobe-Japan1","n":"CID+4001"},{"i":917761,"t":1,"c":"Adobe-Japan1","n":"CID+13514"},{"i":917762,"t":1,"c":"Adobe-Japan1","n":"CID+14091"},{"i":917763,"t":1,"c":"Hanyo-Denshi","n":"JA4657"},{"i":917763,"t":1,"c":"Moji_Joho","n":"MJ027679"},{"i":917764,"t":1,"c":"Hanyo-Denshi","n":"KS474580"},{"i":917764,"t":1,"c":"Moji_Joho","n":"MJ027678"},{"i":917765,"t":1,"c":"Moji_Joho","n":"MJ027680"}]},"A4":{"t":1,"n":"CJK UNIFIED IDEOGRAPH-96A4","V":[{"i":917760,"t":1,"c":"Adobe-Japan1","n":"CID+15266"}]},"A5":{"t":1,"n":"CJK UNIFIED IDEOGRAPH-96A5","V":[{"i":917760,"t":1,"c":"Adobe-Japan1","n":"CID+17185"}]},"A6":{"t":1,"n":"CJK UNIFIED IDEOGRAPH-96A6","V":[{"i":917760,"t":1,"c":"Adobe-Japan1","n":"CID+22841"}]},"A7":{"t":1,"n":"CJK UNIFIED IDEOGRAPH-96A7","V":[{"i":917760,"t":1,"c":"Adobe-Japan1","n":"CID+7108"},{"i":917761,"t":1,"c":"Adobe-Japan1","n":"CID+20244"},{"i":917762,"t":1,"c":"Hanyo-Denshi","n":"JA8011"},{"i":917762,"t":1,"c":"Moji_Joho","n":"MJ027685"},{"i":917763,"t":1,"c":"Hanyo-Denshi","n":"FT2664"},{"i":917763,"t":1,"c":"Moji_Joho","n":"MJ027686"},{"i":917764,"t":1,"c":"Hanyo-Denshi","n":"IB1028"},{"i":917764,"t":1,"c":"Moji_Joho","n":"MJ027684"},{"i":917765,"t":1,"c":"Hanyo-Denshi","n":"JTBE87"},{"i":917765,"t":1,"c":"Moji_Joho","n":"MJ027687"}]},"A8":{"t":1,"n":"CJK UNIFIED IDEOGRAPH-96A8","V":[{"i":917760,"t":1,"c":"Adobe-Japan1","n":"CID+6923"},{"i":917761,"t":1,"c":"Hanyo-Denshi","n":"JA7814"},{"i":917761,"t":1,"c":"Moji_Joho","n":"MJ027689"},{"i":917762,"t":1,"c":"Hanyo-Denshi","n":"FT2625"},{"i":917762,"t":1,"c":"Moji_Joho","n":"MJ027688"}]},"A9":{"t":1,"n":"CJK UNIFIED IDEOGRAPH-96A9","V":[{"i":917760,"t":1,"c":"Adobe-Japan1","n":"CID+15267"}]},"AA":{"t":1,"n":"CJK UNIFIED IDEOGRAPH-96AA","V":[{"i":917760,"t":1,"c":"Adobe-Japan1","n":"CID+7107"},{"i":917761,"t":1,"c":"Hanyo-Denshi","n":"JA8010"},{"i":917761,"t":1,"c":"Moji_Joho","n":"MJ027691"},{"i":917762,"t":1,"c":"Hanyo-Denshi","n":"KS474460"},{"i":917762,"t":1,"c":"Moji_Joho","n":"MJ058977"}]},"AE":{"t":1,"n":"CJK UNIFIED IDEOGRAPH-96AE","V":[{"i":917760,"t":1,"c":"Adobe-Japan1","n":"CID+19964"}]},"AF":{"t":1,"n":"CJK UNIFIED IDEOGRAPH-96AF","V":[{"i":917760,"t":1,"c":"Adobe-Japan1","n":"CID+8689"}]},"B0":{"t":1,"n":"CJK UNIFIED IDEOGRAPH-96B0","V":[{"i":917760,"t":1,"c":"Adobe-Japan1","n":"CID+7111"}]},"B1":{"t":1,"n":"CJK UNIFIED IDEOGRAPH-96B1","V":[{"i":917760,"t":1,"c":"Adobe-Japan1","n":"CID+7109"},{"i":917761,"t":1,"c":"Hanyo-Denshi","n":"JA8012"},{"i":917761,"t":1,"c":"Moji_Joho","n":"MJ027698"},{"i":917762,"t":1,"c":"Hanyo-Denshi","n":"FT2665"},{"i":917762,"t":1,"c":"Moji_Joho","n":"MJ027699"}]},"B2":{"t":1,"n":"CJK UNIFIED IDEOGRAPH-96B2","V":[{"i":917760,"t":1,"c":"Adobe-Japan1","n":"CID+7110"},{"i":917761,"t":1,"c":"Adobe-Japan1","n":"CID+14257"}]},"B3":{"t":1,"n":"CJK UNIFIED IDEOGRAPH-96B3","V":[{"i":917760,"t":1,"c":"Adobe-Japan1","n":"CID+18899"}]},"B4":{"t":1,"n":"CJK UNIFIED IDEOGRAPH-96B4","V":[{"i":917760,"t":1,"c":"Adobe-Japan1","n":"CID+7112"},{"i":917761,"t":1,"c":"Hanyo-Denshi","n":"JA8015"},{"i":917761,"t":1,"c":"Moji_Joho","n":"MJ027702"},{"i":917762,"t":1,"c":"Hanyo-Denshi","n":"KS475300"},{"i":917762,"t":1,"c":"Moji_Joho","n":"MJ027703"}]},"B6":{"t":1,"n":"CJK UNIFIED IDEOGRAPH-96B6","V":[{"i":917760,"t":1,"c":"Adobe-Japan1","n":"CID+7113"},{"i":917761,"t":1,"c":"Hanyo-Denshi","n":"JA8016"},{"i":917761,"t":1,"c":"Moji_Joho","n":"MJ027706"},{"i":917762,"t":1,"c":"Hanyo-Denshi","n":"KS475490"},{"i":917762,"t":1,"c":"Moji_Joho","n":"MJ027705"},{"i":917763,"t":1,"c":"MSARG","n":"MA_90C4"},{"i":917764,"t":1,"c":"MSARG","n":"ME_96B6_001"}]},"B7":{"t":1,"n":"CJK UNIFIED IDEOGRAPH-96B7","V":[{"i":65024,"t":2,"c":3,"n":"CJK COMPATIBILITY IDEOGRAPH-FA2F"},{"i":917760,"t":1,"c":"Adobe-Japan1","n":"CID+4020"}]},"B8":{"t":1,"n":"CJK UNIFIED IDEOGRAPH-96B8","V":[{"i":65024,"t":2,"c":3,"n":"CJK COMPATIBILITY IDEOGRAPH-F9B8"},{"i":917760,"t":1,"c":"Adobe-Japan1","n":"CID+7114"}]},"B9":{"t":1,"n":"CJK UNIFIED IDEOGRAPH-96B9","V":[{"i":917760,"t":1,"c":"Adobe-Japan1","n":"CID+7115"},{"i":917761,"t":1,"c":"Moji_Joho","n":"MJ027709"},{"i":917762,"t":1,"c":"Moji_Joho","n":"MJ056921"}]},"BA":{"t":1,"n":"CJK UNIFIED IDEOGRAPH-96BA","V":[{"i":917760,"t":1,"c":"Adobe-Japan1","n":"CID+18900"}]},"BB":{"t":1,"n":"CJK UNIFIED IDEOGRAPH-96BB","V":[{"i":917760,"t":1,"c":"Adobe-Japan1","n":"CID+2669"},{"i":917761,"t":1,"c":"Adobe-Japan1","n":"CID+13877"},{"i":917762,"t":1,"c":"Moji_Joho","n":"MJ027711"},{"i":917763,"t":1,"c":"Moji_Joho","n":"MJ027712"}]},"BC":{"t":1,"n":"CJK UNIFIED IDEOGRAPH-96BC","V":[{"i":917760,"t":1,"c":"Adobe-Japan1","n":"CID+3407"}]},"BD":{"t":1,"n":"CJK UNIFIED IDEOGRAPH-96BD","V":[{"i":917760,"t":1,"c":"Adobe-Japan1","n":"CID+18901"}]},"C0":{"t":1,"n":"CJK UNIFIED IDEOGRAPH-96C0","V":[{"i":917760,"t":1,"c":"Adobe-Japan1","n":"CID+2627"}]},"C1":{"t":1,"n":"CJK UNIFIED IDEOGRAPH-96C1","V":[{"i":917760,"t":1,"c":"Adobe-Japan1","n":"CID+1571"}]},"C3":{"t":1,"n":"CJK UNIFIED IDEOGRAPH-96C3","V":[{"i":65024,"t":2,"c":3,"n":"CJK COMPATIBILITY IDEOGRAPH-2F9F3"}]},"C4":{"t":1,"n":"CJK UNIFIED IDEOGRAPH-96C4","V":[{"i":917760,"t":1,"c":"Adobe-Japan1","n":"CID+3876"}]},"C5":{"t":1,"n":"CJK UNIFIED IDEOGRAPH-96C5","V":[{"i":917760,"t":1,"c":"Adobe-Japan1","n":"CID+1389"},{"i":917761,"t":1,"c":"Adobe-Japan1","n":"CID+13420"},{"i":917762,"t":1,"c":"Adobe-Japan1","n":"CID+13671"},{"i":917763,"t":1,"c":"Hanyo-Denshi","n":"JA1877"},{"i":917763,"t":1,"c":"Moji_Joho","n":"MJ027722"},{"i":917764,"t":1,"c":"Hanyo-Denshi","n":"KS475980"},{"i":917764,"t":1,"c":"Moji_Joho","n":"MJ027721"},{"i":917765,"t":1,"c":"Moji_Joho","n":"MJ027723"}]},"C6":{"t":1,"n":"CJK UNIFIED IDEOGRAPH-96C6","V":[{"i":917760,"t":1,"c":"Adobe-Japan1","n":"CID+2370"}]},"C7":{"t":1,"n":"CJK UNIFIED IDEOGRAPH-96C7","V":[{"i":917760,"t":1,"c":"Adobe-Japan1","n":"CID+1935"},{"i":917761,"t":1,"c":"Adobe-Japan1","n":"CID+13758"},{"i":917762,"t":1,"c":"Hanyo-Denshi","n":"JA2459"},{"i":917762,"t":1,"c":"Moji_Joho","n":"MJ027726"},{"i":917763,"t":1,"c":"Hanyo-Denshi","n":"JTBE8C"},{"i":917763,"t":1,"c":"Moji_Joho","n":"MJ027725"}]},"C9":{"t":1,"n":"CJK UNIFIED IDEOGRAPH-96C9","V":[{"i":917760,"t":1,"c":"Adobe-Japan1","n":"CID+7118"}]},"CA":{"t":1,"n":"CJK UNIFIED IDEOGRAPH-96CA","V":[{"i":917760,"t":1,"c":"Adobe-Japan1","n":"CID+22842"}]},"CB":{"t":1,"n":"CJK UNIFIED IDEOGRAPH-96CB","V":[{"i":917760,"t":1,"c":"Adobe-Japan1","n":"CID+7117"}]},"CC":{"t":1,"n":"CJK UNIFIED IDEOGRAPH-96CC","V":[{"i":917760,"t":1,"c":"Adobe-Japan1","n":"CID+2241"},{"i":917761,"t":1,"c":"Moji_Joho","n":"MJ027731"},{"i":917762,"t":1,"c":"Moji_Joho","n":"MJ027732"}]},"CD":{"t":1,"n":"CJK UNIFIED IDEOGRAPH-96CD","V":[{"i":917760,"t":1,"c":"Adobe-Japan1","n":"CID+7119"},{"i":917761,"t":1,"c":"Hanyo-Denshi","n":"JA8022"},{"i":917762,"t":1,"c":"Hanyo-Denshi","n":"TK01096410"}]},"CE":{"t":1,"n":"CJK UNIFIED IDEOGRAPH-96CE","V":[{"i":917760,"t":1,"c":"Adobe-Japan1","n":"CID+7116"}]},"D1":{"t":1,"n":"CJK UNIFIED IDEOGRAPH-96D1","V":[{"i":917760,"t":1,"c":"Adobe-Japan1","n":"CID+2166"}]},"D2":{"t":1,"n":"CJK UNIFIED IDEOGRAPH-96D2","V":[{"i":917760,"t":1,"c":"Adobe-Japan1","n":"CID+15268"}]},"D5":{"t":1,"n":"CJK UNIFIED IDEOGRAPH-96D5","V":[{"i":917760,"t":1,"c":"Adobe-Japan1","n":"CID+7123"},{"i":917761,"t":1,"c":"Hanyo-Denshi","n":"JA8026"},{"i":917761,"t":1,"c":"Moji_Joho","n":"MJ027741"},{"i":917762,"t":1,"c":"Hanyo-Denshi","n":"FT2666"},{"i":917762,"t":1,"c":"Moji_Joho","n":"MJ027742"}]},"D6":{"t":1,"n":"CJK UNIFIED IDEOGRAPH-96D6","V":[{"i":917760,"t":1,"c":"Adobe-Japan1","n":"CID+6546"}]},"D8":{"t":1,"n":"CJK UNIFIED IDEOGRAPH-96D8","V":[{"i":917760,"t":1,"c":"Adobe-Japan1","n":"CID+18904"},{"i":917761,"t":1,"c":"Hanyo-Denshi","n":"JB7085"},{"i":917761,"t":1,"c":"Moji_Joho","n":"MJ027747"},{"i":917762,"t":1,"c":"Hanyo-Denshi","n":"KS477730"},{"i":917762,"t":1,"c":"Moji_Joho","n":"MJ027746"},{"i":917763,"t":1,"c":"Hanyo-Denshi","n":"KS477510"},{"i":917763,"t":1,"c":"Moji_Joho","n":"MJ027745"},{"i":917764,"t":1,"c":"Moji_Joho","n":"MJ027748"}]},"D9":{"t":1,"n":"CJK UNIFIED IDEOGRAPH-96D9","V":[{"i":917760,"t":1,"c":"Adobe-Japan1","n":"CID+4331"},{"i":917761,"t":1,"c":"Adobe-Japan1","n":"CID+13525"},{"i":917762,"t":1,"c":"Moji_Joho","n":"MJ027749"},{"i":917763,"t":1,"c":"Moji_Joho","n":"MJ027750"}]},"DA":{"t":1,"n":"CJK UNIFIED IDEOGRAPH-96DA","V":[{"i":917760,"t":1,"c":"Adobe-Japan1","n":"CID+18905"},{"i":917761,"t":1,"c":"Adobe-Japan1","n":"CID+22843"},{"i":917762,"t":1,"c":"Hanyo-Denshi","n":"JB7086"},{"i":917762,"t":1,"c":"Moji_Joho","n":"MJ027752"},{"i":917763,"t":1,"c":"Hanyo-Denshi","n":"KS477710"},{"i":917763,"t":1,"c":"Moji_Joho","n":"MJ027753"},{"i":917764,"t":1,"c":"Hanyo-Denshi","n":"JD9183"},{"i":917764,"t":1,"c":"Moji_Joho","n":"MJ027751"}]},"DB":{"t":1,"n":"CJK UNIFIED IDEOGRAPH-96DB","V":[{"i":917760,"t":1,"c":"Adobe-Japan1","n":"CID+2621"}]},"DC":{"t":1,"n":"CJK UNIFIED IDEOGRAPH-96DC","V":[{"i":917760,"t":1,"c":"Adobe-Japan1","n":"CID+7121"}]},"DD":{"t":1,"n":"CJK UNIFIED IDEOGRAPH-96DD","V":[{"i":917760,"t":1,"c":"Adobe-Japan1","n":"CID+18906"}]},"DE":{"t":1,"n":"CJK UNIFIED IDEOGRAPH-96DE","V":[{"i":917760,"t":1,"c":"Adobe-Japan1","n":"CID+15270"}]},"DF":{"t":1,"n":"CJK UNIFIED IDEOGRAPH-96DF","V":[{"i":917760,"t":1,"c":"Adobe-Japan1","n":"CID+22844"}]},"E2":{"t":1,"n":"CJK UNIFIED IDEOGRAPH-96E2","V":[{"i":65024,"t":2,"c":3,"n":"CJK COMPATIBILITY IDEOGRAPH-F9EA"},{"i":917760,"t":1,"c":"Adobe-Japan1","n":"CID+3949"},{"i":917761,"t":1,"c":"Hanyo-Denshi","n":"JA4605"},{"i":917761,"t":1,"c":"Moji_Joho","n":"MJ027760"},{"i":917762,"t":1,"c":"Hanyo-Denshi","n":"KS477960"},{"i":917762,"t":1,"c":"Moji_Joho","n":"MJ027761"}]},"E3":{"t":1,"n":"CJK UNIFIED IDEOGRAPH-96E3","V":[{"i":65024,"t":2,"c":3,"n":"CJK COMPATIBILITY IDEOGRAPH-FA68"},{"i":65025,"t":2,"c":3,"n":"CJK COMPATIBILITY IDEOGRAPH-FAC7"},{"i":917760,"t":1,"c":"Adobe-Japan1","n":"CID+13374"},{"i":917761,"t":1,"c":"Adobe-Japan1","n":"CID+3273"},{"i":917762,"t":1,"c":"Hanyo-Denshi","n":"JA3881"},{"i":917762,"t":1,"c":"Moji_Joho","n":"MJ027762"},{"i":917763,"t":1,"c":"Hanyo-Denshi","n":"IB1030"},{"i":917763,"t":1,"c":"Moji_Joho","n":"MJ058984"},{"i":917764,"t":1,"c":"Hanyo-Denshi","n":"JC9367"},{"i":917764,"t":1,"c":"Moji_Joho","n":"MJ030304"},{"i":917765,"t":1,"c":"Hanyo-Denshi","n":"TK01096670"},{"i":917766,"t":1,"c":"Hanyo-Denshi","n":"TK01096700"},{"i":917767,"t":1,"c":"Hanyo-Denshi","n":"TK01096710"},{"i":917768,"t":1,"c":"Moji_Joho","n":"MJ058983"}]},"E8":{"t":1,"n":"CJK UNIFIED IDEOGRAPH-96E8","V":[{"i":917760,"t":1,"c":"Adobe-Japan1","n":"CID+1229"},{"i":917761,"t":1,"c":"Adobe-Japan1","n":"CID+13645"},{"i":917762,"t":1,"c":"Hanyo-Denshi","n":"JA1711"},{"i":917762,"t":1,"c":"Moji_Joho","n":"MJ027770"},{"i":917763,"t":1,"c":"Hanyo-Denshi","n":"IB1031"},{"i":917763,"t":1,"c":"Moji_Joho","n":"MJ027771"}]},"E9":{"t":1,"n":"CJK UNIFIED IDEOGRAPH-96E9","V":[{"i":917760,"t":1,"c":"Adobe-Japan1","n":"CID+15271"},{"i":917761,"t":1,"c":"Hanyo-Denshi","n":"JB7090"},{"i":917761,"t":1,"c":"Moji_Joho","n":"MJ027772"},{"i":917762,"t":1,"c":"Hanyo-Denshi","n":"KS478810"},{"i":917762,"t":1,"c":"Moji_Joho","n":"MJ027773"}]},"EA":{"t":1,"n":"CJK UNIFIED IDEOGRAPH-96EA","V":[{"i":917760,"t":1,"c":"Adobe-Japan1","n":"CID+2695"},{"i":917761,"t":1,"c":"Adobe-Japan1","n":"CID+13881"},{"i":917762,"t":1,"c":"Hanyo-Denshi","n":"JA3267"},{"i":917762,"t":1,"c":"Moji_Joho","n":"MJ027775"},{"i":917763,"t":1,"c":"Hanyo-Denshi","n":"JTBE98"},{"i":917763,"t":1,"c":"Moji_Joho","n":"MJ027774"},{"i":917764,"t":1,"c":"Hanyo-Denshi","n":"TK01096830"},{"i":917765,"t":1,"c":"Hanyo-Denshi","n":"TK01096840"}]},"EB":{"t":1,"n":"CJK UNIFIED IDEOGRAPH-96EB","V":[{"i":917760,"t":1,"c":"Adobe-Japan1","n":"CID+2274"}]},"EF":{"t":1,"n":"CJK UNIFIED IDEOGRAPH-96EF","V":[{"i":917760,"t":1,"c":"Adobe-Japan1","n":"CID+17186"},{"i":917761,"t":1,"c":"Moji_Joho","n":"MJ027781"},{"i":917762,"t":1,"c":"Moji_Joho","n":"MJ027782"}]},"F0":{"t":1,"n":"CJK UNIFIED IDEOGRAPH-96F0","V":[{"i":917760,"t":1,"c":"Adobe-Japan1","n":"CID+3591"},{"i":917761,"t":1,"c":"Adobe-Japan1","n":"CID+13504"},{"i":917762,"t":1,"c":"Hanyo-Denshi","n":"JA4223"},{"i":917762,"t":1,"c":"Moji_Joho","n":"MJ027783"},{"i":917763,"t":1,"c":"Hanyo-Denshi","n":"FT1671"},{"i":917763,"t":1,"c":"Moji_Joho","n":"MJ027784"}]},"F1":{"t":1,"n":"CJK UNIFIED IDEOGRAPH-96F1","V":[{"i":917760,"t":1,"c":"Adobe-Japan1","n":"CID+15272"}]},"F2":{"t":1,"n":"CJK UNIFIED IDEOGRAPH-96F2","V":[{"i":917760,"t":1,"c":"Adobe-Japan1","n":"CID+1250"}]},"F6":{"t":1,"n":"CJK UNIFIED IDEOGRAPH-96F6","V":[{"i":65024,"t":2,"c":3,"n":"CJK COMPATIBILITY IDEOGRAPH-F9B2"},{"i":917760,"t":1,"c":"Adobe-Japan1","n":"CID+4021"}]},"F7":{"t":1,"n":"CJK UNIFIED IDEOGRAPH-96F7","V":[{"i":65024,"t":2,"c":3,"n":"CJK COMPATIBILITY IDEOGRAPH-F949"},{"i":917760,"t":1,"c":"Adobe-Japan1","n":"CID+3925"},{"i":917761,"t":1,"c":"Hanyo-Denshi","n":"JA4575"},{"i":917762,"t":1,"c":"Hanyo-Denshi","n":"TK01096890"}]},"F9":{"t":1,"n":"CJK UNIFIED IDEOGRAPH-96F9","V":[{"i":917760,"t":1,"c":"Adobe-Japan1","n":"CID+7124"},{"i":917761,"t":1,"c":"Hanyo-Denshi","n":"JA8027"},{"i":917761,"t":1,"c":"Moji_Joho","n":"MJ027793"},{"i":917762,"t":1,"c":"Hanyo-Denshi","n":"FT2667S"},{"i":917762,"t":1,"c":"Moji_Joho","n":"MJ027794"}]},"FA":{"t":1,"n":"CJK UNIFIED IDEOGRAPH-96FA","V":[{"i":917760,"t":1,"c":"Adobe-Japan1","n":"CID+22845"}]},"FB":{"t":1,"n":"CJK UNIFIED IDEOGRAPH-96FB","V":[{"i":917760,"t":1,"c":"Adobe-Japan1","n":"CID+3135"}]}}