{"4B":{"t":1,"n":"CJK UNIFIED IDEOGRAPH-25C4B","V":[{"i":917760,"t":1,"c":"Adobe-Japan1","n":"CID+18302"},{"i":917761,"t":1,"c":"Hanyo-Denshi","n":"JD8361"},{"i":917761,"t":1,"c":"Moji_Joho","n":"MJ043882"},{"i":917762,"t":1,"c":"Hanyo-Denshi","n":"JTB7C0"},{"i":917762,"t":1,"c":"Moji_Joho","n":"MJ060022"}]},"64":{"t":1,"n":"CJK UNIFIED IDEOGRAPH-25C64","V":[{"i":917760,"t":1,"c":"Adobe-Japan1","n":"CID+18303"}]},"7A":{"t":1,"n":"CJK UNIFIED IDEOGRAPH-25C7A","V":[{"i":917760,"t":1,"c":"Hanyo-Denshi","n":"KS295200"},{"i":917761,"t":1,"c":"Hanyo-Denshi","n":"TK01070410"}]},"80":{"t":1,"n":"CJK UNIFIED IDEOGRAPH-25C80","V":[{"i":65024,"t":2,"c":3,"n":"CJK COMPATIBILITY IDEOGRAPH-2F965"},{"i":917760,"t":1,"c":"Hanyo-Denshi","n":"KS295440"},{"i":917760,"t":1,"c":"Moji_Joho","n":"MJ043899"},{"i":917761,"t":1,"c":"Hanyo-Denshi","n":"KS298040"},{"i":917761,"t":1,"c":"Moji_Joho","n":"MJ043900"}]},"C9":{"t":1,"n":"CJK UNIFIED IDEOGRAPH-25CC9","V":[{"i":917760,"t":1,"c":"Hanyo-Denshi","n":"KS296250"},{"i":917761,"t":1,"c":"Hanyo-Denshi","n":"TK01070330"}]},"CC":{"t":1,"n":"CJK UNIFIED IDEOGRAPH-25CCC","V":[{"i":917760,"t":1,"c":"Hanyo-Denshi","n":"KS296320"},{"i":917761,"t":1,"c":"Hanyo-Denshi","n":"TK01070390"}]},"CD":{"t":1,"n":"CJK UNIFIED IDEOGRAPH-25CCD","V":[{"i":917760,"t":1,"c":"Hanyo-Denshi","n":"KS296330"},{"i":917761,"t":1,"c":"Hanyo-Denshi","n":"TK01070430"}]},"CF":{"t":1,"n":"CJK UNIFIED IDEOGRAPH-25CCF","V":[{"i":917760,"t":1,"c":"Hanyo-Denshi","n":"KS296360"},{"i":917761,"t":1,"c":"Hanyo-Denshi","n":"TK01070400"}]},"D0":{"t":1,"n":"CJK UNIFIED IDEOGRAPH-25CD0","V":[{"i":65024,"t":2,"c":3,"n":"CJK COMPATIBILITY IDEOGRAPH-FAD6"}]}}